{
  "source_url": "https://www.ariteks.net/arbir-200.asp",
  "source_category_url": "https://www.ariteks.net/protection-technical-textiles.asp",
  "commercial_name": "ArBir 200",
  "product_name": "ArBir 200",
  "title_descriptor": "Knit Fabric for Safety Clothes",
  "slug": "arbir-200",
  "page_title": "Knit Fabric for Safety Clothes - ArBir 200 - Ariteks",
  "spec_line": "220 g/m², 100% Polyester, High Visible, Woven Like Knit Fabric",
  "description_blocks": [
    "%100 polyester, 220 g/m², developed for jackets, raincoats and reflective strips base",
    "EN ISO 20471 certified.",
    "Neon dyed fabrics they attract more attention than other colors. They absorb uv light and reflect as a visible light.",
    "As a result they shine more than other objects."
  ],
  "technical_parameters": [
    {
      "name": "Fiber",
      "value": "100% Polyester (PES)",
      "standard": "EN ISO 2076",
      "source_table_index": 6
    },
    {
      "name": "Yarn",
      "value": "100 Denier",
      "standard": "EN ISO 2060",
      "source_table_index": 6
    },
    {
      "name": "Weight",
      "value": "220 ±10 g/m²",
      "standard": "EN ISO 3081",
      "source_table_index": 6
    },
    {
      "name": "Width",
      "value": "1500 ±20 mm",
      "standard": "EN ISO 3932",
      "source_table_index": 6
    },
    {
      "name": "Bursting strength",
      "value": "> 1500 kPa (kN/m² )",
      "standard": "EN ISO 13938-1",
      "source_table_index": 6
    },
    {
      "name": "Dimensional Change",
      "value": "-5% < Length < +5% ; -5% < Width < +5%",
      "standard": "EN ISO 5077",
      "source_table_index": 6
    },
    {
      "name": "Rubbing Fastness",
      "value": "4-5",
      "standard": "EN ISO 105 X12",
      "source_table_index": 6
    },
    {
      "name": "Perspiration Fastness",
      "value": "4-5",
      "standard": "EN ISO 105 E04",
      "source_table_index": 6
    },
    {
      "name": "Washing Fastness",
      "value": "4-5",
      "standard": "EN ISO 105 C06",
      "source_table_index": 6
    },
    {
      "name": "Dry Cleaning Fastness",
      "value": "4-5",
      "standard": "EN ISO 105 D01",
      "source_table_index": 6
    },
    {
      "name": "Hypochlorite Fastness",
      "value": "4-5",
      "standard": "EN ISO 105 N01",
      "source_table_index": 6
    },
    {
      "name": "Hot Press Fastness",
      "value": "4-5",
      "standard": "EN ISO 105 X11",
      "source_table_index": 6
    },
    {
      "name": "pH",
      "value": "6.2",
      "standard": "EN ISO 3071",
      "source_table_index": 6
    },
    {
      "name": "Azo Test",
      "value": "No Azo Colorants.",
      "standard": "EN ISO 14362-1",
      "source_table_index": 6
    },
    {
      "name": "Application",
      "value": "Raincoat, Jacket, Parka",
      "standard": "",
      "source_table_index": 6
    },
    {
      "name": "Quality Management",
      "value": "Done",
      "standard": "ISO 9001",
      "source_table_index": 6
    },
    {
      "name": "High Visibility",
      "value": "Done",
      "standard": "EN ISO 20471",
      "source_table_index": 6
    }
  ],
  "technical_documents": [
    {
      "url": "https://www.ariteks.net/pdf/arbir-200-ds.pdf",
      "label": ">> ArBir 200 Data Sheet",
      "title": "",
      "is_asset": true,
      "is_document": true,
      "is_image": false,
      "is_product_page": false,
      "context_text": "Technical Parameters Fiber 100% Polyester (PES) EN ISO 2076 Yarn 100 Denier EN ISO 2060 Weight 220 ±10 g/m² EN ISO 3081 Width 1500 ±20 mm EN ISO 3932 Bursting strength > 1500 kPa (kN/m² ) EN ISO 13938-1 Dimensional Change -5% < Length < +5% ; -5% < Width < +5% EN ISO 5077 Rubbing Fastness 4-5 EN ISO 105 X12 Perspiration Fastness 4-5 EN ISO 105 E04 Washing Fastness 4-5 EN ISO 105 C06 Dry Cleaning Fastness 4-5 EN ISO 105 D01 Hypochlorite Fastness 4-5 EN ISO 105 N01 Hot Press Fastness 4-5 EN ISO 105 X11 pH 6.2 EN ISO 3071 Azo Test No Azo Colorants. EN ISO 14362-1 Application Raincoat, Jacket, Parka Quality Management Done ISO 9001 High Visibility Done EN ISO 20471 Technical Documents >> ArBir 200 Data Sheet Certificates",
      "document_kind": "data_sheet",
      "raw_local_path": "C:\\Projekty\\galia-navi\\_scraped\\fabrics_complete\\arbir-200\\documents\\arbir-200-ds__9745ed45f6.pdf",
      "public_local_path": "C:\\Projekty\\galia-navi\\public\\ariteks\\fabrics\\arbir-200\\documents\\arbir-200-ds__9745ed45f6.pdf",
      "public_url": "/ariteks/fabrics/arbir-200/documents/arbir-200-ds__9745ed45f6.pdf",
      "content_type": "application/pdf",
      "size_bytes": 307021,
      "sha1": "0e5342372470fc5eb2a5160e454f1e5299b2e328"
    }
  ],
  "images": [
    {
      "url": "https://www.ariteks.net/images/lang_flags/tr_s.png",
      "alt": "Turkish",
      "title": "Turkish",
      "context_text": "",
      "classification": "layout_asset",
      "raw_local_path": "C:\\Projekty\\galia-navi\\_scraped\\fabrics_complete\\arbir-200\\images\\tr-s__2229569dd5.png",
      "public_local_path": "C:\\Projekty\\galia-navi\\public\\ariteks\\fabrics\\arbir-200\\images\\tr-s__2229569dd5.png",
      "public_url": "/ariteks/fabrics/arbir-200/images/tr-s__2229569dd5.png",
      "content_type": "image/png",
      "size_bytes": 17432,
      "sha1": "bd65b8e80542cd227cd4804519f1b2f5475ab5ac"
    },
    {
      "url": "https://www.ariteks.net/images/lang_flags/ru_s.png",
      "alt": "Russian",
      "title": "Russian",
      "context_text": "",
      "classification": "layout_asset",
      "raw_local_path": "C:\\Projekty\\galia-navi\\_scraped\\fabrics_complete\\arbir-200\\images\\ru-s__28dde2a24b.png",
      "public_local_path": "C:\\Projekty\\galia-navi\\public\\ariteks\\fabrics\\arbir-200\\images\\ru-s__28dde2a24b.png",
      "public_url": "/ariteks/fabrics/arbir-200/images/ru-s__28dde2a24b.png",
      "content_type": "image/png",
      "size_bytes": 11546,
      "sha1": "32c5e6a1b5d35279db604afc74155714d4620697"
    },
    {
      "url": "https://www.ariteks.net/images/lang_flags/en_s.png",
      "alt": "English",
      "title": "English",
      "context_text": "",
      "classification": "layout_asset",
      "raw_local_path": "C:\\Projekty\\galia-navi\\_scraped\\fabrics_complete\\arbir-200\\images\\en-s__0126e84202.png",
      "public_local_path": "C:\\Projekty\\galia-navi\\public\\ariteks\\fabrics\\arbir-200\\images\\en-s__0126e84202.png",
      "public_url": "/ariteks/fabrics/arbir-200/images/en-s__0126e84202.png",
      "content_type": "image/png",
      "size_bytes": 19703,
      "sha1": "39e2601f0ea48218abc98576c338648d16b981eb"
    },
    {
      "url": "https://www.ariteks.net/images/logo/ariteks_logo_2023_en_s.jpg",
      "alt": "Arıteks Logo",
      "title": "",
      "context_text": "",
      "classification": "layout_asset",
      "raw_local_path": "C:\\Projekty\\galia-navi\\_scraped\\fabrics_complete\\arbir-200\\images\\ariteks-logo-2023-en-s__6098ac7c7f.jpg",
      "public_local_path": "C:\\Projekty\\galia-navi\\public\\ariteks\\fabrics\\arbir-200\\images\\ariteks-logo-2023-en-s__6098ac7c7f.jpg",
      "public_url": "/ariteks/fabrics/arbir-200/images/ariteks-logo-2023-en-s__6098ac7c7f.jpg",
      "content_type": "image/jpeg",
      "size_bytes": 38222,
      "sha1": "7ed77fbb457d1d6a54526ef032e0ea51a86af3da"
    },
    {
      "url": "https://www.ariteks.net/images/techteksposters/protection_m.jpg",
      "alt": "Protection Technical Textiles",
      "title": "Protection Technical Textiles",
      "context_text": "High visible, waterproof, flame retardant, antistatic, chemical resistant workwear fabrics.",
      "classification": "category_banner",
      "raw_local_path": "C:\\Projekty\\galia-navi\\_scraped\\fabrics_complete\\arbir-200\\images\\protection-m__4be43ea90a.jpg",
      "public_local_path": "C:\\Projekty\\galia-navi\\public\\ariteks\\fabrics\\arbir-200\\images\\protection-m__4be43ea90a.jpg",
      "public_url": "/ariteks/fabrics/arbir-200/images/protection-m__4be43ea90a.jpg",
      "content_type": "image/jpeg",
      "size_bytes": 1853151,
      "sha1": "f564b17d0c2bdc1aadb9ce74f47e82397478eb64"
    },
    {
      "url": "https://www.ariteks.net/images/product/arbir_200_main_pic_m.jpg",
      "alt": "Flat Surface Warp Knit Fabric",
      "title": "Flat Surface Warp Knit Fabric",
      "context_text": "%100 polyester, 220 g/m², developed for jackets, raincoats and reflective strips base. EN ISO 20471 certified. Neon dyed fabrics they attract more attention than other colors. They absorb uv light and reflect as a visible light. As a result they shine more than other objects.",
      "classification": "hero_image",
      "raw_local_path": "C:\\Projekty\\galia-navi\\_scraped\\fabrics_complete\\arbir-200\\images\\arbir-200-main-pic-m__65072819fe.jpg",
      "public_local_path": "C:\\Projekty\\galia-navi\\public\\ariteks\\fabrics\\arbir-200\\images\\arbir-200-main-pic-m__65072819fe.jpg",
      "public_url": "/ariteks/fabrics/arbir-200/images/arbir-200-main-pic-m__65072819fe.jpg",
      "content_type": "image/jpeg",
      "size_bytes": 122005,
      "sha1": "7da7fcaa597207b316c4dbf8eecc76838fe4522c"
    },
    {
      "url": "https://www.ariteks.net/images/product/protection_arbir/arbir_200_2_m.jpg",
      "alt": "Orange Fabric Based Reflective Strip",
      "title": "Orange Fabric Based Reflective Strip",
      "context_text": "Applications",
      "classification": "application_image",
      "raw_local_path": "C:\\Projekty\\galia-navi\\_scraped\\fabrics_complete\\arbir-200\\images\\arbir-200-2-m__2059185886.jpg",
      "public_local_path": "C:\\Projekty\\galia-navi\\public\\ariteks\\fabrics\\arbir-200\\images\\arbir-200-2-m__2059185886.jpg",
      "public_url": "/ariteks/fabrics/arbir-200/images/arbir-200-2-m__2059185886.jpg",
      "content_type": "image/jpeg",
      "size_bytes": 10630,
      "sha1": "2c4e1968a489ea957c4c864621c8ca56c6a33e65"
    },
    {
      "url": "https://www.ariteks.net/images/product/protection_arbir/arbir_200_4_m.jpg",
      "alt": "Yellow Fabric Based Reflective Strip",
      "title": "Yellow Fabric Based Reflective Strip",
      "context_text": "Applications",
      "classification": "application_image",
      "raw_local_path": "C:\\Projekty\\galia-navi\\_scraped\\fabrics_complete\\arbir-200\\images\\arbir-200-4-m__bb90e13cf5.jpg",
      "public_local_path": "C:\\Projekty\\galia-navi\\public\\ariteks\\fabrics\\arbir-200\\images\\arbir-200-4-m__bb90e13cf5.jpg",
      "public_url": "/ariteks/fabrics/arbir-200/images/arbir-200-4-m__bb90e13cf5.jpg",
      "content_type": "image/jpeg",
      "size_bytes": 8067,
      "sha1": "a134a8f331bd0a216d08d746e953369985d3ff02"
    },
    {
      "url": "https://www.ariteks.net/images/product/protection_arbir/arbir_200_5_m.jpg",
      "alt": "Navy Fabric Based Reflective Strip",
      "title": "Navy Fabric Based Reflective Strip",
      "context_text": "Applications",
      "classification": "application_image",
      "raw_local_path": "C:\\Projekty\\galia-navi\\_scraped\\fabrics_complete\\arbir-200\\images\\arbir-200-5-m__a89974d6ca.jpg",
      "public_local_path": "C:\\Projekty\\galia-navi\\public\\ariteks\\fabrics\\arbir-200\\images\\arbir-200-5-m__a89974d6ca.jpg",
      "public_url": "/ariteks/fabrics/arbir-200/images/arbir-200-5-m__a89974d6ca.jpg",
      "content_type": "image/jpeg",
      "size_bytes": 8981,
      "sha1": "aa4c02ef4e80e824642b5e65cbbc8ec436b62ff2"
    },
    {
      "url": "https://www.ariteks.net/images/functions/oekoteks_standard_100_s.jpg",
      "alt": "Oeko Tex Standard 100",
      "title": "Oeko Tex Standard 100",
      "context_text": "Functions",
      "classification": "function_icon",
      "raw_local_path": "C:\\Projekty\\galia-navi\\_scraped\\fabrics_complete\\arbir-200\\images\\oekoteks-standard-100-s__ea5e91d474.jpg",
      "public_local_path": "C:\\Projekty\\galia-navi\\public\\ariteks\\fabrics\\arbir-200\\images\\oekoteks-standard-100-s__ea5e91d474.jpg",
      "public_url": "/ariteks/fabrics/arbir-200/images/oekoteks-standard-100-s__ea5e91d474.jpg",
      "content_type": "image/jpeg",
      "size_bytes": 54001,
      "sha1": "66018f06a237c3ddcbf31a5764c82e862dfa9854"
    },
    {
      "url": "https://www.ariteks.net/images/functions/en_20471.jpg",
      "alt": "EN 20471",
      "title": "EN 20471",
      "context_text": "Functions",
      "classification": "function_icon",
      "raw_local_path": "C:\\Projekty\\galia-navi\\_scraped\\fabrics_complete\\arbir-200\\images\\en-20471__b3c86afe25.jpg",
      "public_local_path": "C:\\Projekty\\galia-navi\\public\\ariteks\\fabrics\\arbir-200\\images\\en-20471__b3c86afe25.jpg",
      "public_url": "/ariteks/fabrics/arbir-200/images/en-20471__b3c86afe25.jpg",
      "content_type": "image/jpeg",
      "size_bytes": 9328,
      "sha1": "d9329fb0ea6e52503c8b2b46b21b8ac035618e24"
    },
    {
      "url": "https://www.ariteks.net/images/care_instructions/60_mach_wash_ma_agi.jpg",
      "alt": "60'C Machine Wash",
      "title": "60'C Machine Wash",
      "context_text": "Care Instructions",
      "classification": "care_instruction",
      "raw_local_path": "C:\\Projekty\\galia-navi\\_scraped\\fabrics_complete\\arbir-200\\images\\60-mach-wash-ma-agi__cdc86ecf03.jpg",
      "public_local_path": "C:\\Projekty\\galia-navi\\public\\ariteks\\fabrics\\arbir-200\\images\\60-mach-wash-ma-agi__cdc86ecf03.jpg",
      "public_url": "/ariteks/fabrics/arbir-200/images/60-mach-wash-ma-agi__cdc86ecf03.jpg",
      "content_type": "image/jpeg",
      "size_bytes": 97254,
      "sha1": "5172828b46e8d14500d23799c64ca5370bcf514b"
    },
    {
      "url": "https://www.ariteks.net/images/care_instructions/no_chlorine_bleach.jpg",
      "alt": "No Chlorine Based Bleaching",
      "title": "No Chlorine Based Bleaching",
      "context_text": "Care Instructions",
      "classification": "care_instruction",
      "raw_local_path": "C:\\Projekty\\galia-navi\\_scraped\\fabrics_complete\\arbir-200\\images\\no-chlorine-bleach__33a0308671.jpg",
      "public_local_path": "C:\\Projekty\\galia-navi\\public\\ariteks\\fabrics\\arbir-200\\images\\no-chlorine-bleach__33a0308671.jpg",
      "public_url": "/ariteks/fabrics/arbir-200/images/no-chlorine-bleach__33a0308671.jpg",
      "content_type": "image/jpeg",
      "size_bytes": 97254,
      "sha1": "04121b8c5d4d25547de9c83657618e8fa04d2e52"
    },
    {
      "url": "https://www.ariteks.net/images/care_instructions/tumble_dried_low_ht.jpg",
      "alt": "Can Be Tumble Dried On Low Heat Setting",
      "title": "Can Be Tumble Dried On Low Heat Setting",
      "context_text": "Care Instructions",
      "classification": "care_instruction",
      "raw_local_path": "C:\\Projekty\\galia-navi\\_scraped\\fabrics_complete\\arbir-200\\images\\tumble-dried-low-ht__cd432a52a7.jpg",
      "public_local_path": "C:\\Projekty\\galia-navi\\public\\ariteks\\fabrics\\arbir-200\\images\\tumble-dried-low-ht__cd432a52a7.jpg",
      "public_url": "/ariteks/fabrics/arbir-200/images/tumble-dried-low-ht__cd432a52a7.jpg",
      "content_type": "image/jpeg",
      "size_bytes": 97254,
      "sha1": "b5fb112a29efca36c0a736eb588a8a367fb30bac"
    },
    {
      "url": "https://www.ariteks.net/images/care_instructions/ma_150_iron.jpg",
      "alt": "Maximum 150'C Warm Iron",
      "title": "Maximum 150'C Warm Iron",
      "context_text": "Care Instructions",
      "classification": "care_instruction",
      "raw_local_path": "C:\\Projekty\\galia-navi\\_scraped\\fabrics_complete\\arbir-200\\images\\ma-150-iron__78883199be.jpg",
      "public_local_path": "C:\\Projekty\\galia-navi\\public\\ariteks\\fabrics\\arbir-200\\images\\ma-150-iron__78883199be.jpg",
      "public_url": "/ariteks/fabrics/arbir-200/images/ma-150-iron__78883199be.jpg",
      "content_type": "image/jpeg",
      "size_bytes": 97794,
      "sha1": "f5a4fac2b95005ea49edbeb1b6de2be8abcea782"
    },
    {
      "url": "https://www.ariteks.net/images/care_instructions/dry_cleaning.jpg",
      "alt": "Suitable for Dry Cleaning",
      "title": "Suitable for Dry Cleaning",
      "context_text": "Care Instructions",
      "classification": "care_instruction",
      "raw_local_path": "C:\\Projekty\\galia-navi\\_scraped\\fabrics_complete\\arbir-200\\images\\dry-cleaning__6e8a85520f.jpg",
      "public_local_path": "C:\\Projekty\\galia-navi\\public\\ariteks\\fabrics\\arbir-200\\images\\dry-cleaning__6e8a85520f.jpg",
      "public_url": "/ariteks/fabrics/arbir-200/images/dry-cleaning__6e8a85520f.jpg",
      "content_type": "image/jpeg",
      "size_bytes": 97254,
      "sha1": "d8d03b8658bc4f973c36cb18f135e6b56f318f6c"
    }
  ],
  "image_groups": {
    "hero_images": [
      {
        "url": "https://www.ariteks.net/images/product/arbir_200_main_pic_m.jpg",
        "alt": "Flat Surface Warp Knit Fabric",
        "title": "Flat Surface Warp Knit Fabric",
        "context_text": "%100 polyester, 220 g/m², developed for jackets, raincoats and reflective strips base. EN ISO 20471 certified. Neon dyed fabrics they attract more attention than other colors. They absorb uv light and reflect as a visible light. As a result they shine more than other objects.",
        "classification": "hero_image",
        "raw_local_path": "C:\\Projekty\\galia-navi\\_scraped\\fabrics_complete\\arbir-200\\images\\arbir-200-main-pic-m__65072819fe.jpg",
        "public_local_path": "C:\\Projekty\\galia-navi\\public\\ariteks\\fabrics\\arbir-200\\images\\arbir-200-main-pic-m__65072819fe.jpg",
        "public_url": "/ariteks/fabrics/arbir-200/images/arbir-200-main-pic-m__65072819fe.jpg",
        "content_type": "image/jpeg",
        "size_bytes": 122005,
        "sha1": "7da7fcaa597207b316c4dbf8eecc76838fe4522c"
      }
    ],
    "product_images": [],
    "fabric_photos": [],
    "application_images": [
      {
        "url": "https://www.ariteks.net/images/product/protection_arbir/arbir_200_2_m.jpg",
        "alt": "Orange Fabric Based Reflective Strip",
        "title": "Orange Fabric Based Reflective Strip",
        "context_text": "Applications",
        "classification": "application_image",
        "raw_local_path": "C:\\Projekty\\galia-navi\\_scraped\\fabrics_complete\\arbir-200\\images\\arbir-200-2-m__2059185886.jpg",
        "public_local_path": "C:\\Projekty\\galia-navi\\public\\ariteks\\fabrics\\arbir-200\\images\\arbir-200-2-m__2059185886.jpg",
        "public_url": "/ariteks/fabrics/arbir-200/images/arbir-200-2-m__2059185886.jpg",
        "content_type": "image/jpeg",
        "size_bytes": 10630,
        "sha1": "2c4e1968a489ea957c4c864621c8ca56c6a33e65"
      },
      {
        "url": "https://www.ariteks.net/images/product/protection_arbir/arbir_200_4_m.jpg",
        "alt": "Yellow Fabric Based Reflective Strip",
        "title": "Yellow Fabric Based Reflective Strip",
        "context_text": "Applications",
        "classification": "application_image",
        "raw_local_path": "C:\\Projekty\\galia-navi\\_scraped\\fabrics_complete\\arbir-200\\images\\arbir-200-4-m__bb90e13cf5.jpg",
        "public_local_path": "C:\\Projekty\\galia-navi\\public\\ariteks\\fabrics\\arbir-200\\images\\arbir-200-4-m__bb90e13cf5.jpg",
        "public_url": "/ariteks/fabrics/arbir-200/images/arbir-200-4-m__bb90e13cf5.jpg",
        "content_type": "image/jpeg",
        "size_bytes": 8067,
        "sha1": "a134a8f331bd0a216d08d746e953369985d3ff02"
      },
      {
        "url": "https://www.ariteks.net/images/product/protection_arbir/arbir_200_5_m.jpg",
        "alt": "Navy Fabric Based Reflective Strip",
        "title": "Navy Fabric Based Reflective Strip",
        "context_text": "Applications",
        "classification": "application_image",
        "raw_local_path": "C:\\Projekty\\galia-navi\\_scraped\\fabrics_complete\\arbir-200\\images\\arbir-200-5-m__a89974d6ca.jpg",
        "public_local_path": "C:\\Projekty\\galia-navi\\public\\ariteks\\fabrics\\arbir-200\\images\\arbir-200-5-m__a89974d6ca.jpg",
        "public_url": "/ariteks/fabrics/arbir-200/images/arbir-200-5-m__a89974d6ca.jpg",
        "content_type": "image/jpeg",
        "size_bytes": 8981,
        "sha1": "aa4c02ef4e80e824642b5e65cbbc8ec436b62ff2"
      }
    ],
    "function_icons": [
      {
        "url": "https://www.ariteks.net/images/functions/oekoteks_standard_100_s.jpg",
        "alt": "Oeko Tex Standard 100",
        "title": "Oeko Tex Standard 100",
        "context_text": "Functions",
        "classification": "function_icon",
        "raw_local_path": "C:\\Projekty\\galia-navi\\_scraped\\fabrics_complete\\arbir-200\\images\\oekoteks-standard-100-s__ea5e91d474.jpg",
        "public_local_path": "C:\\Projekty\\galia-navi\\public\\ariteks\\fabrics\\arbir-200\\images\\oekoteks-standard-100-s__ea5e91d474.jpg",
        "public_url": "/ariteks/fabrics/arbir-200/images/oekoteks-standard-100-s__ea5e91d474.jpg",
        "content_type": "image/jpeg",
        "size_bytes": 54001,
        "sha1": "66018f06a237c3ddcbf31a5764c82e862dfa9854"
      },
      {
        "url": "https://www.ariteks.net/images/functions/en_20471.jpg",
        "alt": "EN 20471",
        "title": "EN 20471",
        "context_text": "Functions",
        "classification": "function_icon",
        "raw_local_path": "C:\\Projekty\\galia-navi\\_scraped\\fabrics_complete\\arbir-200\\images\\en-20471__b3c86afe25.jpg",
        "public_local_path": "C:\\Projekty\\galia-navi\\public\\ariteks\\fabrics\\arbir-200\\images\\en-20471__b3c86afe25.jpg",
        "public_url": "/ariteks/fabrics/arbir-200/images/en-20471__b3c86afe25.jpg",
        "content_type": "image/jpeg",
        "size_bytes": 9328,
        "sha1": "d9329fb0ea6e52503c8b2b46b21b8ac035618e24"
      }
    ],
    "certificate_badges": [],
    "care_instructions": [
      {
        "url": "https://www.ariteks.net/images/care_instructions/60_mach_wash_ma_agi.jpg",
        "alt": "60'C Machine Wash",
        "title": "60'C Machine Wash",
        "context_text": "Care Instructions",
        "classification": "care_instruction",
        "raw_local_path": "C:\\Projekty\\galia-navi\\_scraped\\fabrics_complete\\arbir-200\\images\\60-mach-wash-ma-agi__cdc86ecf03.jpg",
        "public_local_path": "C:\\Projekty\\galia-navi\\public\\ariteks\\fabrics\\arbir-200\\images\\60-mach-wash-ma-agi__cdc86ecf03.jpg",
        "public_url": "/ariteks/fabrics/arbir-200/images/60-mach-wash-ma-agi__cdc86ecf03.jpg",
        "content_type": "image/jpeg",
        "size_bytes": 97254,
        "sha1": "5172828b46e8d14500d23799c64ca5370bcf514b"
      },
      {
        "url": "https://www.ariteks.net/images/care_instructions/no_chlorine_bleach.jpg",
        "alt": "No Chlorine Based Bleaching",
        "title": "No Chlorine Based Bleaching",
        "context_text": "Care Instructions",
        "classification": "care_instruction",
        "raw_local_path": "C:\\Projekty\\galia-navi\\_scraped\\fabrics_complete\\arbir-200\\images\\no-chlorine-bleach__33a0308671.jpg",
        "public_local_path": "C:\\Projekty\\galia-navi\\public\\ariteks\\fabrics\\arbir-200\\images\\no-chlorine-bleach__33a0308671.jpg",
        "public_url": "/ariteks/fabrics/arbir-200/images/no-chlorine-bleach__33a0308671.jpg",
        "content_type": "image/jpeg",
        "size_bytes": 97254,
        "sha1": "04121b8c5d4d25547de9c83657618e8fa04d2e52"
      },
      {
        "url": "https://www.ariteks.net/images/care_instructions/tumble_dried_low_ht.jpg",
        "alt": "Can Be Tumble Dried On Low Heat Setting",
        "title": "Can Be Tumble Dried On Low Heat Setting",
        "context_text": "Care Instructions",
        "classification": "care_instruction",
        "raw_local_path": "C:\\Projekty\\galia-navi\\_scraped\\fabrics_complete\\arbir-200\\images\\tumble-dried-low-ht__cd432a52a7.jpg",
        "public_local_path": "C:\\Projekty\\galia-navi\\public\\ariteks\\fabrics\\arbir-200\\images\\tumble-dried-low-ht__cd432a52a7.jpg",
        "public_url": "/ariteks/fabrics/arbir-200/images/tumble-dried-low-ht__cd432a52a7.jpg",
        "content_type": "image/jpeg",
        "size_bytes": 97254,
        "sha1": "b5fb112a29efca36c0a736eb588a8a367fb30bac"
      },
      {
        "url": "https://www.ariteks.net/images/care_instructions/ma_150_iron.jpg",
        "alt": "Maximum 150'C Warm Iron",
        "title": "Maximum 150'C Warm Iron",
        "context_text": "Care Instructions",
        "classification": "care_instruction",
        "raw_local_path": "C:\\Projekty\\galia-navi\\_scraped\\fabrics_complete\\arbir-200\\images\\ma-150-iron__78883199be.jpg",
        "public_local_path": "C:\\Projekty\\galia-navi\\public\\ariteks\\fabrics\\arbir-200\\images\\ma-150-iron__78883199be.jpg",
        "public_url": "/ariteks/fabrics/arbir-200/images/ma-150-iron__78883199be.jpg",
        "content_type": "image/jpeg",
        "size_bytes": 97794,
        "sha1": "f5a4fac2b95005ea49edbeb1b6de2be8abcea782"
      },
      {
        "url": "https://www.ariteks.net/images/care_instructions/dry_cleaning.jpg",
        "alt": "Suitable for Dry Cleaning",
        "title": "Suitable for Dry Cleaning",
        "context_text": "Care Instructions",
        "classification": "care_instruction",
        "raw_local_path": "C:\\Projekty\\galia-navi\\_scraped\\fabrics_complete\\arbir-200\\images\\dry-cleaning__6e8a85520f.jpg",
        "public_local_path": "C:\\Projekty\\galia-navi\\public\\ariteks\\fabrics\\arbir-200\\images\\dry-cleaning__6e8a85520f.jpg",
        "public_url": "/ariteks/fabrics/arbir-200/images/dry-cleaning__6e8a85520f.jpg",
        "content_type": "image/jpeg",
        "size_bytes": 97254,
        "sha1": "d8d03b8658bc4f973c36cb18f135e6b56f318f6c"
      }
    ],
    "structure_images": [],
    "technology_partners": [],
    "category_banners": [
      {
        "url": "https://www.ariteks.net/images/techteksposters/protection_m.jpg",
        "alt": "Protection Technical Textiles",
        "title": "Protection Technical Textiles",
        "context_text": "High visible, waterproof, flame retardant, antistatic, chemical resistant workwear fabrics.",
        "classification": "category_banner",
        "raw_local_path": "C:\\Projekty\\galia-navi\\_scraped\\fabrics_complete\\arbir-200\\images\\protection-m__4be43ea90a.jpg",
        "public_local_path": "C:\\Projekty\\galia-navi\\public\\ariteks\\fabrics\\arbir-200\\images\\protection-m__4be43ea90a.jpg",
        "public_url": "/ariteks/fabrics/arbir-200/images/protection-m__4be43ea90a.jpg",
        "content_type": "image/jpeg",
        "size_bytes": 1853151,
        "sha1": "f564b17d0c2bdc1aadb9ce74f47e82397478eb64"
      }
    ],
    "layout_assets": [
      {
        "url": "https://www.ariteks.net/images/lang_flags/tr_s.png",
        "alt": "Turkish",
        "title": "Turkish",
        "context_text": "",
        "classification": "layout_asset",
        "raw_local_path": "C:\\Projekty\\galia-navi\\_scraped\\fabrics_complete\\arbir-200\\images\\tr-s__2229569dd5.png",
        "public_local_path": "C:\\Projekty\\galia-navi\\public\\ariteks\\fabrics\\arbir-200\\images\\tr-s__2229569dd5.png",
        "public_url": "/ariteks/fabrics/arbir-200/images/tr-s__2229569dd5.png",
        "content_type": "image/png",
        "size_bytes": 17432,
        "sha1": "bd65b8e80542cd227cd4804519f1b2f5475ab5ac"
      },
      {
        "url": "https://www.ariteks.net/images/lang_flags/ru_s.png",
        "alt": "Russian",
        "title": "Russian",
        "context_text": "",
        "classification": "layout_asset",
        "raw_local_path": "C:\\Projekty\\galia-navi\\_scraped\\fabrics_complete\\arbir-200\\images\\ru-s__28dde2a24b.png",
        "public_local_path": "C:\\Projekty\\galia-navi\\public\\ariteks\\fabrics\\arbir-200\\images\\ru-s__28dde2a24b.png",
        "public_url": "/ariteks/fabrics/arbir-200/images/ru-s__28dde2a24b.png",
        "content_type": "image/png",
        "size_bytes": 11546,
        "sha1": "32c5e6a1b5d35279db604afc74155714d4620697"
      },
      {
        "url": "https://www.ariteks.net/images/lang_flags/en_s.png",
        "alt": "English",
        "title": "English",
        "context_text": "",
        "classification": "layout_asset",
        "raw_local_path": "C:\\Projekty\\galia-navi\\_scraped\\fabrics_complete\\arbir-200\\images\\en-s__0126e84202.png",
        "public_local_path": "C:\\Projekty\\galia-navi\\public\\ariteks\\fabrics\\arbir-200\\images\\en-s__0126e84202.png",
        "public_url": "/ariteks/fabrics/arbir-200/images/en-s__0126e84202.png",
        "content_type": "image/png",
        "size_bytes": 19703,
        "sha1": "39e2601f0ea48218abc98576c338648d16b981eb"
      },
      {
        "url": "https://www.ariteks.net/images/logo/ariteks_logo_2023_en_s.jpg",
        "alt": "Arıteks Logo",
        "title": "",
        "context_text": "",
        "classification": "layout_asset",
        "raw_local_path": "C:\\Projekty\\galia-navi\\_scraped\\fabrics_complete\\arbir-200\\images\\ariteks-logo-2023-en-s__6098ac7c7f.jpg",
        "public_local_path": "C:\\Projekty\\galia-navi\\public\\ariteks\\fabrics\\arbir-200\\images\\ariteks-logo-2023-en-s__6098ac7c7f.jpg",
        "public_url": "/ariteks/fabrics/arbir-200/images/ariteks-logo-2023-en-s__6098ac7c7f.jpg",
        "content_type": "image/jpeg",
        "size_bytes": 38222,
        "sha1": "7ed77fbb457d1d6a54526ef032e0ea51a86af3da"
      }
    ],
    "other_images": []
  },
  "colors_and_articles": [
    {
      "color": "Yellow",
      "code_or_pind": "PT-23603",
      "finish": "- HIGH VISIBLE -",
      "article_number": "ArBir 200-5155",
      "raw_lines": {
        "color": "Yellow",
        "code_or_pind": "PT-23603",
        "finish": "- HIGH VISIBLE -",
        "article_number": "ArBir 200-5155"
      }
    },
    {
      "color": "Green",
      "code_or_pind": "PT-22971",
      "finish": "- HIGH VISIBLE -",
      "article_number": "ArBir 200-5156",
      "raw_lines": {
        "color": "Green",
        "code_or_pind": "PT-22971",
        "finish": "- HIGH VISIBLE -",
        "article_number": "ArBir 200-5156"
      }
    },
    {
      "color": "Orange",
      "code_or_pind": "PT-22970",
      "finish": "- HIGH VISIBLE -",
      "article_number": "ArBir 200-5157",
      "raw_lines": {
        "color": "Orange",
        "code_or_pind": "PT-22970",
        "finish": "- HIGH VISIBLE -",
        "article_number": "ArBir 200-5157"
      }
    },
    {
      "color": "Red",
      "code_or_pind": "PT-33280-1",
      "finish": "- HIGH VISIBLE -",
      "article_number": "ArBir 200-5158",
      "raw_lines": {
        "color": "Red",
        "code_or_pind": "PT-33280-1",
        "finish": "- HIGH VISIBLE -",
        "article_number": "ArBir 200-5158"
      }
    },
    {
      "color": "Dark Red",
      "code_or_pind": "PT-33354",
      "finish": "- STANDARD -",
      "article_number": "ArBir 200-5159",
      "raw_lines": {
        "color": "Dark Red",
        "code_or_pind": "PT-33354",
        "finish": "- STANDARD -",
        "article_number": "ArBir 200-5159"
      }
    },
    {
      "color": "Royal",
      "code_or_pind": "PT-57820",
      "finish": "- STANDARD -",
      "article_number": "ArBir 200-5160",
      "raw_lines": {
        "color": "Royal",
        "code_or_pind": "PT-57820",
        "finish": "- STANDARD -",
        "article_number": "ArBir 200-5160"
      }
    },
    {
      "color": "Navy",
      "code_or_pind": "PT-57753",
      "finish": "- STANDARD -",
      "article_number": "ArBir 200-5161",
      "raw_lines": {
        "color": "Navy",
        "code_or_pind": "PT-57753",
        "finish": "- STANDARD -",
        "article_number": "ArBir 200-5161"
      }
    },
    {
      "color": "Green",
      "code_or_pind": "PT-64889",
      "finish": "- STANDARD -",
      "article_number": "ArBir 200-5162",
      "raw_lines": {
        "color": "Green",
        "code_or_pind": "PT-64889",
        "finish": "- STANDARD -",
        "article_number": "ArBir 200-5162"
      }
    },
    {
      "color": "Grey",
      "code_or_pind": "PT-95502",
      "finish": "- STANDARD -",
      "article_number": "ArBir 200-5163",
      "raw_lines": {
        "color": "Grey",
        "code_or_pind": "PT-95502",
        "finish": "- STANDARD -",
        "article_number": "ArBir 200-5163"
      }
    },
    {
      "color": "Black",
      "code_or_pind": "PT-95503",
      "finish": "- STANDARD -",
      "article_number": "ArBir 200-5164",
      "raw_lines": {
        "color": "Black",
        "code_or_pind": "PT-95503",
        "finish": "- STANDARD -",
        "article_number": "ArBir 200-5164"
      }
    },
    {
      "color": "Sax",
      "code_or_pind": "PT-57972",
      "finish": "- STANDARD -",
      "article_number": "ArBir 200-5165",
      "raw_lines": {
        "color": "Sax",
        "code_or_pind": "PT-57972",
        "finish": "- STANDARD -",
        "article_number": "ArBir 200-5165"
      }
    }
  ],
  "links": [
    {
      "url": "http://tr.ariteks.net/arbir-200.asp",
      "label": "",
      "title": "",
      "is_asset": false,
      "is_document": false,
      "is_image": false,
      "is_product_page": true,
      "context_text": "",
      "raw_local_path": "",
      "public_local_path": "",
      "public_url": "",
      "content_type": "",
      "size_bytes": "",
      "sha1": ""
    },
    {
      "url": "http://ru.ariteks.net/arbir-200.asp",
      "label": "",
      "title": "",
      "is_asset": false,
      "is_document": false,
      "is_image": false,
      "is_product_page": true,
      "context_text": "",
      "raw_local_path": "",
      "public_local_path": "",
      "public_url": "",
      "content_type": "",
      "size_bytes": "",
      "sha1": ""
    },
    {
      "url": "http://en.ariteks.net/arbir-200.asp",
      "label": "",
      "title": "",
      "is_asset": false,
      "is_document": false,
      "is_image": false,
      "is_product_page": true,
      "context_text": "",
      "raw_local_path": "",
      "public_local_path": "",
      "public_url": "",
      "content_type": "",
      "size_bytes": "",
      "sha1": ""
    },
    {
      "url": "https://www.ariteks.net/mainpage.asp",
      "label": "",
      "title": "",
      "is_asset": false,
      "is_document": false,
      "is_image": false,
      "is_product_page": false,
      "context_text": "",
      "raw_local_path": "",
      "public_local_path": "",
      "public_url": "",
      "content_type": "",
      "size_bytes": "",
      "sha1": ""
    },
    {
      "url": "https://www.ariteks.net/protection-technical-textiles.asp",
      "label": "",
      "title": "",
      "is_asset": false,
      "is_document": false,
      "is_image": false,
      "is_product_page": false,
      "context_text": "High visible, waterproof, flame retardant, antistatic, chemical resistant workwear fabrics.",
      "raw_local_path": "",
      "public_local_path": "",
      "public_url": "",
      "content_type": "",
      "size_bytes": "",
      "sha1": ""
    },
    {
      "url": "https://www.ariteks.net/pdf/arbir-200-ds.pdf",
      "label": ">> ArBir 200 Data Sheet",
      "title": "",
      "is_asset": true,
      "is_document": true,
      "is_image": false,
      "is_product_page": false,
      "context_text": "Technical Parameters Fiber 100% Polyester (PES) EN ISO 2076 Yarn 100 Denier EN ISO 2060 Weight 220 ±10 g/m² EN ISO 3081 Width 1500 ±20 mm EN ISO 3932 Bursting strength > 1500 kPa (kN/m² ) EN ISO 13938-1 Dimensional Change -5% < Length < +5% ; -5% < Width < +5% EN ISO 5077 Rubbing Fastness 4-5 EN ISO 105 X12 Perspiration Fastness 4-5 EN ISO 105 E04 Washing Fastness 4-5 EN ISO 105 C06 Dry Cleaning Fastness 4-5 EN ISO 105 D01 Hypochlorite Fastness 4-5 EN ISO 105 N01 Hot Press Fastness 4-5 EN ISO 105 X11 pH 6.2 EN ISO 3071 Azo Test No Azo Colorants. EN ISO 14362-1 Application Raincoat, Jacket, Parka Quality Management Done ISO 9001 High Visibility Done EN ISO 20471 Technical Documents >> ArBir 200 Data Sheet Certificates",
      "raw_local_path": "C:\\Projekty\\galia-navi\\_scraped\\fabrics_complete\\arbir-200\\documents\\arbir-200-ds__9745ed45f6.pdf",
      "public_local_path": "C:\\Projekty\\galia-navi\\public\\ariteks\\fabrics\\arbir-200\\documents\\arbir-200-ds__9745ed45f6.pdf",
      "public_url": "/ariteks/fabrics/arbir-200/documents/arbir-200-ds__9745ed45f6.pdf",
      "content_type": "application/pdf",
      "size_bytes": 307021,
      "sha1": "0e5342372470fc5eb2a5160e454f1e5299b2e328"
    },
    {
      "url": "https://www.ariteks.net/images/product/protection_arbir/arbir_200_2.jpg",
      "label": "",
      "title": "",
      "is_asset": true,
      "is_document": false,
      "is_image": true,
      "is_product_page": false,
      "context_text": "Applications",
      "raw_local_path": "C:\\Projekty\\galia-navi\\_scraped\\fabrics_complete\\arbir-200\\images\\arbir-200-2__81b16888f2.jpg",
      "public_local_path": "C:\\Projekty\\galia-navi\\public\\ariteks\\fabrics\\arbir-200\\images\\arbir-200-2__81b16888f2.jpg",
      "public_url": "/ariteks/fabrics/arbir-200/images/arbir-200-2__81b16888f2.jpg",
      "content_type": "image/jpeg",
      "size_bytes": 23118,
      "sha1": "a40468215f2b7fe6599a2f089bda8ae08a126f7a"
    },
    {
      "url": "https://www.ariteks.net/images/product/protection_arbir/arbir_200_4.jpg",
      "label": "",
      "title": "",
      "is_asset": true,
      "is_document": false,
      "is_image": true,
      "is_product_page": false,
      "context_text": "Applications",
      "raw_local_path": "C:\\Projekty\\galia-navi\\_scraped\\fabrics_complete\\arbir-200\\images\\arbir-200-4__0c29755bde.jpg",
      "public_local_path": "C:\\Projekty\\galia-navi\\public\\ariteks\\fabrics\\arbir-200\\images\\arbir-200-4__0c29755bde.jpg",
      "public_url": "/ariteks/fabrics/arbir-200/images/arbir-200-4__0c29755bde.jpg",
      "content_type": "image/jpeg",
      "size_bytes": 35750,
      "sha1": "97a49f8afb960ecd4e8287b4246818523ed2d1ac"
    },
    {
      "url": "https://www.ariteks.net/images/product/protection_arbir/arbir_200_5.jpg",
      "label": "",
      "title": "",
      "is_asset": true,
      "is_document": false,
      "is_image": true,
      "is_product_page": false,
      "context_text": "Applications",
      "raw_local_path": "C:\\Projekty\\galia-navi\\_scraped\\fabrics_complete\\arbir-200\\images\\arbir-200-5__ed986faa63.jpg",
      "public_local_path": "C:\\Projekty\\galia-navi\\public\\ariteks\\fabrics\\arbir-200\\images\\arbir-200-5__ed986faa63.jpg",
      "public_url": "/ariteks/fabrics/arbir-200/images/arbir-200-5__ed986faa63.jpg",
      "content_type": "image/jpeg",
      "size_bytes": 23436,
      "sha1": "b0a95dbfa8e2120b6622e182070392396a7dba91"
    },
    {
      "url": "https://www.ariteks.net/products.asp",
      "label": "Products",
      "title": "",
      "is_asset": false,
      "is_document": false,
      "is_image": false,
      "is_product_page": false,
      "context_text": "Home > Products > Protection > ArBir-200",
      "raw_local_path": "",
      "public_local_path": "",
      "public_url": "",
      "content_type": "",
      "size_bytes": "",
      "sha1": ""
    },
    {
      "url": "https://www.ariteks.net/arbir-200.asp",
      "label": "ArBir-200",
      "title": "",
      "is_asset": false,
      "is_document": false,
      "is_image": false,
      "is_product_page": true,
      "context_text": "Home > Products > Protection > ArBir-200",
      "raw_local_path": "",
      "public_local_path": "",
      "public_url": "",
      "content_type": "",
      "size_bytes": "",
      "sha1": ""
    },
    {
      "url": "https://www.ariteks.net/apparel-fashion-textiles.asp",
      "label": "APPAREL TEXTILES",
      "title": "",
      "is_asset": false,
      "is_document": false,
      "is_image": false,
      "is_product_page": false,
      "context_text": "APPAREL TEXTILES BUILDING TECHNICAL TEXTILES HOME TECHNICAL TEXTILES PROTECTION TECHNICAL TEXTILES MEDICAL TECHNICAL TEXTILES SPORT TECHNICAL TEXTILES TRANSPORT TECHNICAL TEXTILES",
      "raw_local_path": "",
      "public_local_path": "",
      "public_url": "",
      "content_type": "",
      "size_bytes": "",
      "sha1": ""
    },
    {
      "url": "https://www.ariteks.net/building-technical-textiles.asp",
      "label": "BUILDING TECHNICAL TEXTILES",
      "title": "",
      "is_asset": false,
      "is_document": false,
      "is_image": false,
      "is_product_page": false,
      "context_text": "APPAREL TEXTILES BUILDING TECHNICAL TEXTILES HOME TECHNICAL TEXTILES PROTECTION TECHNICAL TEXTILES MEDICAL TECHNICAL TEXTILES SPORT TECHNICAL TEXTILES TRANSPORT TECHNICAL TEXTILES",
      "raw_local_path": "",
      "public_local_path": "",
      "public_url": "",
      "content_type": "",
      "size_bytes": "",
      "sha1": ""
    },
    {
      "url": "https://www.ariteks.net/home-technical-textiles.asp",
      "label": "HOME TECHNICAL TEXTILES",
      "title": "",
      "is_asset": false,
      "is_document": false,
      "is_image": false,
      "is_product_page": false,
      "context_text": "APPAREL TEXTILES BUILDING TECHNICAL TEXTILES HOME TECHNICAL TEXTILES PROTECTION TECHNICAL TEXTILES MEDICAL TECHNICAL TEXTILES SPORT TECHNICAL TEXTILES TRANSPORT TECHNICAL TEXTILES",
      "raw_local_path": "",
      "public_local_path": "",
      "public_url": "",
      "content_type": "",
      "size_bytes": "",
      "sha1": ""
    },
    {
      "url": "https://www.ariteks.net/medical-technical-textiles.asp",
      "label": "MEDICAL TECHNICAL TEXTILES",
      "title": "",
      "is_asset": false,
      "is_document": false,
      "is_image": false,
      "is_product_page": false,
      "context_text": "APPAREL TEXTILES BUILDING TECHNICAL TEXTILES HOME TECHNICAL TEXTILES PROTECTION TECHNICAL TEXTILES MEDICAL TECHNICAL TEXTILES SPORT TECHNICAL TEXTILES TRANSPORT TECHNICAL TEXTILES",
      "raw_local_path": "",
      "public_local_path": "",
      "public_url": "",
      "content_type": "",
      "size_bytes": "",
      "sha1": ""
    },
    {
      "url": "https://www.ariteks.net/sport-technical-textiles.asp",
      "label": "SPORT TECHNICAL TEXTILES",
      "title": "",
      "is_asset": false,
      "is_document": false,
      "is_image": false,
      "is_product_page": false,
      "context_text": "APPAREL TEXTILES BUILDING TECHNICAL TEXTILES HOME TECHNICAL TEXTILES PROTECTION TECHNICAL TEXTILES MEDICAL TECHNICAL TEXTILES SPORT TECHNICAL TEXTILES TRANSPORT TECHNICAL TEXTILES",
      "raw_local_path": "",
      "public_local_path": "",
      "public_url": "",
      "content_type": "",
      "size_bytes": "",
      "sha1": ""
    },
    {
      "url": "https://www.ariteks.net/transport-technical-textiles.asp",
      "label": "TRANSPORT TECHNICAL TEXTILES",
      "title": "",
      "is_asset": false,
      "is_document": false,
      "is_image": false,
      "is_product_page": false,
      "context_text": "APPAREL TEXTILES BUILDING TECHNICAL TEXTILES HOME TECHNICAL TEXTILES PROTECTION TECHNICAL TEXTILES MEDICAL TECHNICAL TEXTILES SPORT TECHNICAL TEXTILES TRANSPORT TECHNICAL TEXTILES",
      "raw_local_path": "",
      "public_local_path": "",
      "public_url": "",
      "content_type": "",
      "size_bytes": "",
      "sha1": ""
    },
    {
      "url": "https://www.ariteks.net/ariteksgrup.asp",
      "label": "ARITEKS GROUP",
      "title": "",
      "is_asset": false,
      "is_document": false,
      "is_image": false,
      "is_product_page": false,
      "context_text": "ARITEKS GROUP SERVICES",
      "raw_local_path": "",
      "public_local_path": "",
      "public_url": "",
      "content_type": "",
      "size_bytes": "",
      "sha1": ""
    },
    {
      "url": "https://www.ariteks.net/service-textile.asp",
      "label": "SERVICES",
      "title": "",
      "is_asset": false,
      "is_document": false,
      "is_image": false,
      "is_product_page": false,
      "context_text": "ARITEKS GROUP SERVICES",
      "raw_local_path": "",
      "public_local_path": "",
      "public_url": "",
      "content_type": "",
      "size_bytes": "",
      "sha1": ""
    },
    {
      "url": "https://www.ariteks.net/service-textile-uv-protection.asp",
      "label": "UV PROTECTION",
      "title": "",
      "is_asset": false,
      "is_document": false,
      "is_image": false,
      "is_product_page": false,
      "context_text": "UV PROTECTION FLAME RETARDANT INSECT REPELLENT ANTIBACTERIAL WATER REPELLENT",
      "raw_local_path": "",
      "public_local_path": "",
      "public_url": "",
      "content_type": "",
      "size_bytes": "",
      "sha1": ""
    },
    {
      "url": "https://www.ariteks.net/service-textile-flame-retardant.asp",
      "label": "FLAME RETARDANT",
      "title": "",
      "is_asset": false,
      "is_document": false,
      "is_image": false,
      "is_product_page": false,
      "context_text": "UV PROTECTION FLAME RETARDANT INSECT REPELLENT ANTIBACTERIAL WATER REPELLENT",
      "raw_local_path": "",
      "public_local_path": "",
      "public_url": "",
      "content_type": "",
      "size_bytes": "",
      "sha1": ""
    },
    {
      "url": "https://www.ariteks.net/service-textile-insect-repellent.asp",
      "label": "INSECT REPELLENT",
      "title": "",
      "is_asset": false,
      "is_document": false,
      "is_image": false,
      "is_product_page": false,
      "context_text": "UV PROTECTION FLAME RETARDANT INSECT REPELLENT ANTIBACTERIAL WATER REPELLENT",
      "raw_local_path": "",
      "public_local_path": "",
      "public_url": "",
      "content_type": "",
      "size_bytes": "",
      "sha1": ""
    },
    {
      "url": "https://www.ariteks.net/service-textile-antibacterial.asp",
      "label": "ANTIBACTERIAL",
      "title": "",
      "is_asset": false,
      "is_document": false,
      "is_image": false,
      "is_product_page": false,
      "context_text": "UV PROTECTION FLAME RETARDANT INSECT REPELLENT ANTIBACTERIAL WATER REPELLENT",
      "raw_local_path": "",
      "public_local_path": "",
      "public_url": "",
      "content_type": "",
      "size_bytes": "",
      "sha1": ""
    },
    {
      "url": "https://www.ariteks.net/service-textile-water-and-soil-repellent.asp",
      "label": "WATER REPELLENT",
      "title": "",
      "is_asset": false,
      "is_document": false,
      "is_image": false,
      "is_product_page": false,
      "context_text": "UV PROTECTION FLAME RETARDANT INSECT REPELLENT ANTIBACTERIAL WATER REPELLENT",
      "raw_local_path": "",
      "public_local_path": "",
      "public_url": "",
      "content_type": "",
      "size_bytes": "",
      "sha1": ""
    },
    {
      "url": "https://www.ariteks.net/ardilight.asp",
      "label": "ARDILIGHT",
      "title": "",
      "is_asset": false,
      "is_document": false,
      "is_image": false,
      "is_product_page": false,
      "context_text": "ARDILIGHT ARNEO ECO AROF FILE",
      "raw_local_path": "",
      "public_local_path": "",
      "public_url": "",
      "content_type": "",
      "size_bytes": "",
      "sha1": ""
    },
    {
      "url": "https://www.ariteks.net/arneo-eco.asp",
      "label": "ARNEO ECO",
      "title": "",
      "is_asset": false,
      "is_document": false,
      "is_image": false,
      "is_product_page": false,
      "context_text": "ARDILIGHT ARNEO ECO AROF FILE",
      "raw_local_path": "",
      "public_local_path": "",
      "public_url": "",
      "content_type": "",
      "size_bytes": "",
      "sha1": ""
    },
    {
      "url": "https://www.ariteks.net/arof-file.asp",
      "label": "AROF FILE",
      "title": "",
      "is_asset": false,
      "is_document": false,
      "is_image": false,
      "is_product_page": false,
      "context_text": "ARDILIGHT ARNEO ECO AROF FILE",
      "raw_local_path": "",
      "public_local_path": "",
      "public_url": "",
      "content_type": "",
      "size_bytes": "",
      "sha1": ""
    },
    {
      "url": "http://www.ariteks.net",
      "label": "www.ariteks.net",
      "title": "",
      "is_asset": false,
      "is_document": false,
      "is_image": false,
      "is_product_page": false,
      "context_text": "Ariteks Headquarters Phone: +90 212 538 05 98 Address: Otakçılar Cad. No:80/32 34050 Eyupsultan/Istanbul Turkiye E-Mail: support@ariteksinfo.com Web: www.ariteks.net",
      "raw_local_path": "",
      "public_local_path": "",
      "public_url": "",
      "content_type": "",
      "size_bytes": "",
      "sha1": ""
    }
  ],
  "tables": [
    {
      "table_index": 3,
      "text_preview": "High visible, waterproof, flame retardant, antistatic, chemical resistant workwear fabrics.",
      "rows": [
        [
          "High visible, waterproof, flame retardant, antistatic, chemical resistant workwear fabrics."
        ]
      ]
    },
    {
      "table_index": 4,
      "text_preview": "Protection Technical Textiles",
      "rows": [
        [
          "Protection Technical Textiles"
        ]
      ]
    },
    {
      "table_index": 5,
      "text_preview": "ArBir 200 220 g/m² , 100% Polyester, High Visible, Woven Like Knit Fabric",
      "rows": [
        [
          "ArBir 200"
        ],
        [
          "220 g/m² , 100% Polyester, High Visible, Woven Like Knit Fabric"
        ]
      ]
    },
    {
      "table_index": 6,
      "text_preview": "Fiber 100% Polyester (PES) EN ISO 2076 Yarn 100 Denier EN ISO 2060 Weight 220 ±10 g/m² EN ISO 3081 Width 1500 ±20 mm EN ISO 3932 Bursting strength > 1500 kPa (kN/m² ) EN ISO 13938-1 Dimensional Change -5% < Length < +5% ; -5% < Width < +5% EN ISO 5077 Rubbing Fastness 4-5 EN ISO 105 X12 Perspiration Fastness 4-5 EN ISO 105 E04 Washing Fastness 4-5 EN ISO 105 C06 Dry Cleaning Fastness 4-5 EN ISO 105 D01 Hypochlorite Fastness 4-5 EN ISO 105 N01 Hot Press Fastness 4-5 EN ISO 105 X11 pH 6.2 EN ISO 3071 Azo Test No Azo Colorants. EN ISO 14362-1 Application Raincoat, Jacket, Parka Quality Management Done ISO 9001 High Visibility Done EN ISO 20471",
      "rows": [
        [
          "Fiber",
          "100% Polyester (PES)",
          "EN ISO 2076"
        ],
        [
          "Yarn",
          "100 Denier",
          "EN ISO 2060"
        ],
        [
          "Weight",
          "220 ±10 g/m²",
          "EN ISO 3081"
        ],
        [
          "Width",
          "1500 ±20 mm",
          "EN ISO 3932"
        ],
        [
          "Bursting strength",
          "> 1500 kPa (kN/m² )",
          "EN ISO 13938-1"
        ],
        [
          "Dimensional Change",
          "-5% < Length < +5% ; -5% < Width < +5%",
          "EN ISO 5077"
        ],
        [
          "Rubbing Fastness",
          "4-5",
          "EN ISO 105 X12"
        ],
        [
          "Perspiration Fastness",
          "4-5",
          "EN ISO 105 E04"
        ],
        [
          "Washing Fastness",
          "4-5",
          "EN ISO 105 C06"
        ],
        [
          "Dry Cleaning Fastness",
          "4-5",
          "EN ISO 105 D01"
        ],
        [
          "Hypochlorite Fastness",
          "4-5",
          "EN ISO 105 N01"
        ],
        [
          "Hot Press Fastness",
          "4-5",
          "EN ISO 105 X11"
        ],
        [
          "pH",
          "6.2",
          "EN ISO 3071"
        ],
        [
          "Azo Test",
          "No Azo Colorants.",
          "EN ISO 14362-1"
        ],
        [
          "Application",
          "Raincoat, Jacket, Parka"
        ],
        [
          "Quality Management",
          "Done",
          "ISO 9001"
        ],
        [
          "High Visibility",
          "Done",
          "EN ISO 20471"
        ]
      ]
    },
    {
      "table_index": 7,
      "text_preview": "Yellow PT-23603 - HIGH VISIBLE - ArBir 200-5155 Green PT-22971 - HIGH VISIBLE - ArBir 200-5156 Orange PT-22970 - HIGH VISIBLE - ArBir 200-5157 Red PT-33280-1 - HIGH VISIBLE - ArBir 200-5158 Dark Red PT-33354 - STANDARD - ArBir 200-5159 Royal PT-57820 - STANDARD - ArBir 200-5160 Navy PT-57753 - STANDARD - ArBir 200-5161 Green PT-64889 - STANDARD - ArBir 200-5162 Grey PT-95502 - STANDARD - ArBir 200-5163 Black PT-95503 - STANDARD - ArBir 200-5164 Sax PT-57972 - STANDARD - ArBir 200-5165",
      "rows": [
        [
          "Yellow",
          "PT-23603",
          "- HIGH VISIBLE -",
          "ArBir 200-5155"
        ],
        [
          "Green",
          "PT-22971",
          "- HIGH VISIBLE -",
          "ArBir 200-5156"
        ],
        [
          "Orange",
          "PT-22970",
          "- HIGH VISIBLE -",
          "ArBir 200-5157"
        ],
        [
          "Red",
          "PT-33280-1",
          "- HIGH VISIBLE -",
          "ArBir 200-5158"
        ],
        [
          "Dark Red",
          "PT-33354",
          "- STANDARD -",
          "ArBir 200-5159"
        ],
        [
          "Royal",
          "PT-57820",
          "- STANDARD -",
          "ArBir 200-5160"
        ],
        [
          "Navy",
          "PT-57753",
          "- STANDARD -",
          "ArBir 200-5161"
        ],
        [
          "Green",
          "PT-64889",
          "- STANDARD -",
          "ArBir 200-5162"
        ],
        [
          "Grey",
          "PT-95502",
          "- STANDARD -",
          "ArBir 200-5163"
        ],
        [
          "Black",
          "PT-95503",
          "- STANDARD -",
          "ArBir 200-5164"
        ],
        [
          "Sax",
          "PT-57972",
          "- STANDARD -",
          "ArBir 200-5165"
        ]
      ]
    },
    {
      "table_index": 8,
      "text_preview": "Home > Products > Protection > ArBir-200",
      "rows": [
        [
          "Home > Products > Protection > ArBir-200"
        ]
      ]
    },
    {
      "table_index": 9,
      "text_preview": "APPAREL TEXTILES BUILDING TECHNICAL TEXTILES HOME TECHNICAL TEXTILES PROTECTION TECHNICAL TEXTILES MEDICAL TECHNICAL TEXTILES SPORT TECHNICAL TEXTILES TRANSPORT TECHNICAL TEXTILES ARITEKS GROUP SERVICES UV PROTECTION FLAME RETARDANT INSECT REPELLENT ANTIBACTERIAL WATER REPELLENT ARDILIGHT ARNEO ECO AROF FILE",
      "rows": [
        [
          "APPAREL TEXTILES BUILDING TECHNICAL TEXTILES HOME TECHNICAL TEXTILES PROTECTION TECHNICAL TEXTILES MEDICAL TECHNICAL TEXTILES SPORT TECHNICAL TEXTILES TRANSPORT TECHNICAL TEXTILES",
          "ARITEKS GROUP SERVICES",
          "UV PROTECTION FLAME RETARDANT INSECT REPELLENT ANTIBACTERIAL WATER REPELLENT",
          "ARDILIGHT ARNEO ECO AROF FILE"
        ]
      ]
    },
    {
      "table_index": 10,
      "text_preview": "Ariteks Headquarters Phone: +90 212 538 05 98 Address: Otakçılar Cad. No:80/32 34050 Eyupsultan/Istanbul Turkiye E-Mail: support@ariteksinfo.com Web: www.ariteks.net",
      "rows": [
        [
          "Ariteks Headquarters Phone: +90 212 538 05 98 Address: Otakçılar Cad. No:80/32 34050 Eyupsultan/Istanbul Turkiye E-Mail: support@ariteksinfo.com Web: www.ariteks.net"
        ]
      ]
    },
    {
      "table_index": 11,
      "text_preview": "Copyright © 2026 Arıteks A.Ş.",
      "rows": [
        [
          "Copyright © 2026 Arıteks A.Ş."
        ]
      ]
    }
  ],
  "text_blocks": [
    {
      "order": 1,
      "tag": "div",
      "text": "High visible, waterproof, flame retardant, antistatic, chemical resistant workwear fabrics. Protection Technical Textiles"
    },
    {
      "order": 2,
      "tag": "div",
      "text": "High visible, waterproof, flame retardant, antistatic, chemical resistant workwear fabrics."
    },
    {
      "order": 3,
      "tag": "td",
      "text": "High visible, waterproof, flame retardant, antistatic, chemical resistant workwear fabrics."
    },
    {
      "order": 4,
      "tag": "h1",
      "text": "High visible, waterproof, flame retardant, antistatic, chemical resistant workwear fabrics."
    },
    {
      "order": 5,
      "tag": "td",
      "text": "Protection Technical Textiles"
    },
    {
      "order": 6,
      "tag": "td",
      "text": "ArBir 200"
    },
    {
      "order": 7,
      "tag": "td",
      "text": "220 g/m² , 100% Polyester, High Visible, Woven Like Knit Fabric"
    },
    {
      "order": 8,
      "tag": "div",
      "text": "%100 polyester, 220 g/m², developed for jackets, raincoats and reflective strips base. EN ISO 20471 certified. Neon dyed fabrics they attract more attention than other colors. They absorb uv light and reflect as a visible light. As a result they shine more than other objects. Technical Parameters Fiber 100% Polyester (PES) EN ISO 2076 Yarn 100 Denier EN ISO 2060 Weight 220 ±10 g/m² EN ISO 3081 Width 1500 ±20 mm EN ISO 3932 Bursting strength > 1500 kPa (kN/m² ) EN ISO 13938-1 Dimensional Change -5% < Length < +5% ; -5% < Width < +5% EN ISO 5077 Rubbing Fastness 4-5 EN ISO 105 X12 Perspiration Fastness 4-5 EN ISO 105 E04 Washing Fastness 4-5 EN ISO 105 C06 Dry Cleaning Fastness 4-5 EN ISO 105 D01 Hypochlorite Fastness 4-5 EN ISO 105 N01 Hot Press Fastness 4-5 EN ISO 105 X11 pH 6.2 EN ISO 3071 Azo Test No Azo Colorants. EN ISO 14362-1 Application Raincoat, Jacket, Parka Quality Management Done ISO 9001 High Visibility Done EN ISO 20471 Technical Documents >> ArBir 200 Data Sheet Certificates"
    },
    {
      "order": 9,
      "tag": "div",
      "text": "%100 polyester, 220 g/m², developed for jackets, raincoats and reflective strips base. EN ISO 20471 certified. Neon dyed fabrics they attract more attention than other colors. They absorb uv light and reflect as a visible light. As a result they shine more than other objects."
    },
    {
      "order": 10,
      "tag": "h1",
      "text": "%100 polyester, 220 g/m², developed for jackets, raincoats and reflective strips base."
    },
    {
      "order": 11,
      "tag": "h2",
      "text": "EN ISO 20471 certified."
    },
    {
      "order": 12,
      "tag": "div",
      "text": "Technical Parameters Fiber 100% Polyester (PES) EN ISO 2076 Yarn 100 Denier EN ISO 2060 Weight 220 ±10 g/m² EN ISO 3081 Width 1500 ±20 mm EN ISO 3932 Bursting strength > 1500 kPa (kN/m² ) EN ISO 13938-1 Dimensional Change -5% < Length < +5% ; -5% < Width < +5% EN ISO 5077 Rubbing Fastness 4-5 EN ISO 105 X12 Perspiration Fastness 4-5 EN ISO 105 E04 Washing Fastness 4-5 EN ISO 105 C06 Dry Cleaning Fastness 4-5 EN ISO 105 D01 Hypochlorite Fastness 4-5 EN ISO 105 N01 Hot Press Fastness 4-5 EN ISO 105 X11 pH 6.2 EN ISO 3071 Azo Test No Azo Colorants. EN ISO 14362-1 Application Raincoat, Jacket, Parka Quality Management Done ISO 9001 High Visibility Done EN ISO 20471 Technical Documents >> ArBir 200 Data Sheet Certificates"
    },
    {
      "order": 13,
      "tag": "td",
      "text": "Fiber"
    },
    {
      "order": 14,
      "tag": "td",
      "text": "100% Polyester (PES)"
    },
    {
      "order": 15,
      "tag": "td",
      "text": "EN ISO 2076"
    },
    {
      "order": 16,
      "tag": "td",
      "text": "Yarn"
    },
    {
      "order": 17,
      "tag": "td",
      "text": "100 Denier"
    },
    {
      "order": 18,
      "tag": "td",
      "text": "EN ISO 2060"
    },
    {
      "order": 19,
      "tag": "td",
      "text": "Weight"
    },
    {
      "order": 20,
      "tag": "td",
      "text": "220 ±10 g/m²"
    },
    {
      "order": 21,
      "tag": "td",
      "text": "EN ISO 3081"
    },
    {
      "order": 22,
      "tag": "td",
      "text": "Width"
    },
    {
      "order": 23,
      "tag": "td",
      "text": "1500 ±20 mm"
    },
    {
      "order": 24,
      "tag": "td",
      "text": "EN ISO 3932"
    },
    {
      "order": 25,
      "tag": "td",
      "text": "Bursting strength"
    },
    {
      "order": 26,
      "tag": "td",
      "text": "> 1500 kPa (kN/m² )"
    },
    {
      "order": 27,
      "tag": "td",
      "text": "EN ISO 13938-1"
    },
    {
      "order": 28,
      "tag": "td",
      "text": "Dimensional Change"
    },
    {
      "order": 29,
      "tag": "td",
      "text": "-5% < Length < +5% ; -5% < Width < +5%"
    },
    {
      "order": 30,
      "tag": "td",
      "text": "EN ISO 5077"
    },
    {
      "order": 31,
      "tag": "td",
      "text": "Rubbing Fastness"
    },
    {
      "order": 32,
      "tag": "td",
      "text": "4-5"
    },
    {
      "order": 33,
      "tag": "td",
      "text": "EN ISO 105 X12"
    },
    {
      "order": 34,
      "tag": "td",
      "text": "Perspiration Fastness"
    },
    {
      "order": 35,
      "tag": "td",
      "text": "4-5"
    },
    {
      "order": 36,
      "tag": "td",
      "text": "EN ISO 105 E04"
    },
    {
      "order": 37,
      "tag": "td",
      "text": "Washing Fastness"
    },
    {
      "order": 38,
      "tag": "td",
      "text": "4-5"
    },
    {
      "order": 39,
      "tag": "td",
      "text": "EN ISO 105 C06"
    },
    {
      "order": 40,
      "tag": "td",
      "text": "Dry Cleaning Fastness"
    },
    {
      "order": 41,
      "tag": "td",
      "text": "4-5"
    },
    {
      "order": 42,
      "tag": "td",
      "text": "EN ISO 105 D01"
    },
    {
      "order": 43,
      "tag": "td",
      "text": "Hypochlorite Fastness"
    },
    {
      "order": 44,
      "tag": "td",
      "text": "4-5"
    },
    {
      "order": 45,
      "tag": "td",
      "text": "EN ISO 105 N01"
    },
    {
      "order": 46,
      "tag": "td",
      "text": "Hot Press Fastness"
    },
    {
      "order": 47,
      "tag": "td",
      "text": "4-5"
    },
    {
      "order": 48,
      "tag": "td",
      "text": "EN ISO 105 X11"
    },
    {
      "order": 49,
      "tag": "td",
      "text": "pH"
    },
    {
      "order": 50,
      "tag": "td",
      "text": "6.2"
    },
    {
      "order": 51,
      "tag": "td",
      "text": "EN ISO 3071"
    },
    {
      "order": 52,
      "tag": "td",
      "text": "Azo Test"
    },
    {
      "order": 53,
      "tag": "td",
      "text": "No Azo Colorants."
    },
    {
      "order": 54,
      "tag": "td",
      "text": "EN ISO 14362-1"
    },
    {
      "order": 55,
      "tag": "td",
      "text": "Application"
    },
    {
      "order": 56,
      "tag": "td",
      "text": "Raincoat, Jacket, Parka"
    },
    {
      "order": 57,
      "tag": "td",
      "text": "Quality Management"
    },
    {
      "order": 58,
      "tag": "td",
      "text": "Done"
    },
    {
      "order": 59,
      "tag": "td",
      "text": "ISO 9001"
    },
    {
      "order": 60,
      "tag": "td",
      "text": "High Visibility"
    },
    {
      "order": 61,
      "tag": "td",
      "text": "Done"
    },
    {
      "order": 62,
      "tag": "td",
      "text": "EN ISO 20471"
    },
    {
      "order": 63,
      "tag": "div",
      "text": "Applications Functions"
    },
    {
      "order": 64,
      "tag": "div",
      "text": "Applications"
    },
    {
      "order": 65,
      "tag": "div",
      "text": "Functions"
    },
    {
      "order": 66,
      "tag": "div",
      "text": "Care Instructions Colors and Article Numbers Yellow PT-23603 - HIGH VISIBLE - ArBir 200-5155 Green PT-22971 - HIGH VISIBLE - ArBir 200-5156 Orange PT-22970 - HIGH VISIBLE - ArBir 200-5157 Red PT-33280-1 - HIGH VISIBLE - ArBir 200-5158 Dark Red PT-33354 - STANDARD - ArBir 200-5159 Royal PT-57820 - STANDARD - ArBir 200-5160 Navy PT-57753 - STANDARD - ArBir 200-5161 Green PT-64889 - STANDARD - ArBir 200-5162 Grey PT-95502 - STANDARD - ArBir 200-5163 Black PT-95503 - STANDARD - ArBir 200-5164 Sax PT-57972 - STANDARD - ArBir 200-5165"
    },
    {
      "order": 67,
      "tag": "div",
      "text": "Care Instructions"
    },
    {
      "order": 68,
      "tag": "div",
      "text": "Colors and Article Numbers Yellow PT-23603 - HIGH VISIBLE - ArBir 200-5155 Green PT-22971 - HIGH VISIBLE - ArBir 200-5156 Orange PT-22970 - HIGH VISIBLE - ArBir 200-5157 Red PT-33280-1 - HIGH VISIBLE - ArBir 200-5158 Dark Red PT-33354 - STANDARD - ArBir 200-5159 Royal PT-57820 - STANDARD - ArBir 200-5160 Navy PT-57753 - STANDARD - ArBir 200-5161 Green PT-64889 - STANDARD - ArBir 200-5162 Grey PT-95502 - STANDARD - ArBir 200-5163 Black PT-95503 - STANDARD - ArBir 200-5164 Sax PT-57972 - STANDARD - ArBir 200-5165"
    },
    {
      "order": 69,
      "tag": "td",
      "text": "Yellow"
    },
    {
      "order": 70,
      "tag": "td",
      "text": "PT-23603"
    },
    {
      "order": 71,
      "tag": "td",
      "text": "- HIGH VISIBLE -"
    },
    {
      "order": 72,
      "tag": "td",
      "text": "ArBir 200-5155"
    },
    {
      "order": 73,
      "tag": "td",
      "text": "Green"
    },
    {
      "order": 74,
      "tag": "td",
      "text": "PT-22971"
    },
    {
      "order": 75,
      "tag": "td",
      "text": "- HIGH VISIBLE -"
    },
    {
      "order": 76,
      "tag": "td",
      "text": "ArBir 200-5156"
    },
    {
      "order": 77,
      "tag": "td",
      "text": "Orange"
    },
    {
      "order": 78,
      "tag": "td",
      "text": "PT-22970"
    },
    {
      "order": 79,
      "tag": "td",
      "text": "- HIGH VISIBLE -"
    },
    {
      "order": 80,
      "tag": "td",
      "text": "ArBir 200-5157"
    },
    {
      "order": 81,
      "tag": "td",
      "text": "Red"
    },
    {
      "order": 82,
      "tag": "td",
      "text": "PT-33280-1"
    },
    {
      "order": 83,
      "tag": "td",
      "text": "- HIGH VISIBLE -"
    },
    {
      "order": 84,
      "tag": "td",
      "text": "ArBir 200-5158"
    },
    {
      "order": 85,
      "tag": "td",
      "text": "Dark Red"
    },
    {
      "order": 86,
      "tag": "td",
      "text": "PT-33354"
    },
    {
      "order": 87,
      "tag": "td",
      "text": "- STANDARD -"
    },
    {
      "order": 88,
      "tag": "td",
      "text": "ArBir 200-5159"
    },
    {
      "order": 89,
      "tag": "td",
      "text": "Royal"
    },
    {
      "order": 90,
      "tag": "td",
      "text": "PT-57820"
    },
    {
      "order": 91,
      "tag": "td",
      "text": "- STANDARD -"
    },
    {
      "order": 92,
      "tag": "td",
      "text": "ArBir 200-5160"
    },
    {
      "order": 93,
      "tag": "td",
      "text": "Navy"
    },
    {
      "order": 94,
      "tag": "td",
      "text": "PT-57753"
    },
    {
      "order": 95,
      "tag": "td",
      "text": "- STANDARD -"
    },
    {
      "order": 96,
      "tag": "td",
      "text": "ArBir 200-5161"
    },
    {
      "order": 97,
      "tag": "td",
      "text": "Green"
    },
    {
      "order": 98,
      "tag": "td",
      "text": "PT-64889"
    },
    {
      "order": 99,
      "tag": "td",
      "text": "- STANDARD -"
    },
    {
      "order": 100,
      "tag": "td",
      "text": "ArBir 200-5162"
    },
    {
      "order": 101,
      "tag": "td",
      "text": "Grey"
    },
    {
      "order": 102,
      "tag": "td",
      "text": "PT-95502"
    },
    {
      "order": 103,
      "tag": "td",
      "text": "- STANDARD -"
    },
    {
      "order": 104,
      "tag": "td",
      "text": "ArBir 200-5163"
    },
    {
      "order": 105,
      "tag": "td",
      "text": "Black"
    },
    {
      "order": 106,
      "tag": "td",
      "text": "PT-95503"
    },
    {
      "order": 107,
      "tag": "td",
      "text": "- STANDARD -"
    },
    {
      "order": 108,
      "tag": "td",
      "text": "ArBir 200-5164"
    },
    {
      "order": 109,
      "tag": "td",
      "text": "Sax"
    },
    {
      "order": 110,
      "tag": "td",
      "text": "PT-57972"
    },
    {
      "order": 111,
      "tag": "td",
      "text": "- STANDARD -"
    },
    {
      "order": 112,
      "tag": "td",
      "text": "ArBir 200-5165"
    },
    {
      "order": 113,
      "tag": "td",
      "text": "Home > Products > Protection > ArBir-200"
    },
    {
      "order": 114,
      "tag": "td",
      "text": "APPAREL TEXTILES BUILDING TECHNICAL TEXTILES HOME TECHNICAL TEXTILES PROTECTION TECHNICAL TEXTILES MEDICAL TECHNICAL TEXTILES SPORT TECHNICAL TEXTILES TRANSPORT TECHNICAL TEXTILES"
    },
    {
      "order": 115,
      "tag": "td",
      "text": "ARITEKS GROUP SERVICES"
    },
    {
      "order": 116,
      "tag": "td",
      "text": "UV PROTECTION FLAME RETARDANT INSECT REPELLENT ANTIBACTERIAL WATER REPELLENT"
    },
    {
      "order": 117,
      "tag": "td",
      "text": "ARDILIGHT ARNEO ECO AROF FILE"
    },
    {
      "order": 118,
      "tag": "td",
      "text": "Ariteks Headquarters Phone: +90 212 538 05 98 Address: Otakçılar Cad. No:80/32 34050 Eyupsultan/Istanbul Turkiye E-Mail: support@ariteksinfo.com Web: www.ariteks.net"
    },
    {
      "order": 119,
      "tag": "td",
      "text": "Copyright © 2026 Arıteks A.Ş."
    }
  ],
  "full_text": "Knit Fabric for Safety Clothes - ArBir 200 - Ariteks\nHigh visible, waterproof, flame retardant, antistatic, chemical resistant workwear fabrics.\nProtection Technical Textiles\nArBir 200\n220 gr/m\n2\n, 100% Polyester, High Visible, Woven Like Knit Fabric\n%100 polyester, 220 g/m², developed for jackets, raincoats and reflective strips base.\nEN ISO 20471 certified.\nNeon dyed fabrics they attract more attention than other colors. They absorb uv light and reflect as a visible light.\nAs a result they shine more than other objects.\nTechnical Parameters\nFiber\n100% Polyester (PES)\nEN ISO 2076\nYarn\n100 Denier\nEN ISO 2060\nWeight\n220 ±10 gr/m\n2\nEN ISO 3081\nWidth\n1500 ±20 mm\nEN ISO 3932\nBursting strength\n> 1500 kPa (kN/m\n2\n)\nEN ISO 13938-1\nDimensional Change\n-5% < Length < +5% ; -5% < Width < +5%\nEN ISO 5077\nRubbing Fastness\n4-5\nEN ISO 105 X12\nPerspiration Fastness\n4-5\nEN ISO 105 E04\nWashing Fastness\n4-5\nEN ISO 105 C06\nDry Cleaning Fastness\n4-5\nEN ISO 105 D01\nHypochlorite Fastness\n4-5\nEN ISO 105 N01\nHot Press Fastness\n4-5\nEN ISO 105 X11\npH\n6.2\nEN ISO 3071\nAzo Test\nNo Azo Colorants.\nEN ISO 14362-1\nApplication\nRaincoat, Jacket, Parka\nQuality Management\nDone\nISO 9001\nHigh Visibility\nDone\nEN ISO 20471\nTechnical Documents\n>> ArBir 200 Data Sheet\nCertificates\nApplications\nFunctions\nCare Instructions\nColors and Article Numbers\nYellow\nPT-23603\n- HIGH VISIBLE -\nArBir 200-5155\nGreen\nPT-22971\n- HIGH VISIBLE -\nArBir 200-5156\nOrange\nPT-22970\n- HIGH VISIBLE -\nArBir 200-5157\nRed\nPT-33280-1\n- HIGH VISIBLE -\nArBir 200-5158\nDark Red\nPT-33354\n- STANDARD -\nArBir 200-5159\nRoyal\nPT-57820\n- STANDARD -\nArBir 200-5160\nNavy\nPT-57753\n- STANDARD -\nArBir 200-5161\nGreen\nPT-64889\n- STANDARD -\nArBir 200-5162\nGrey\nPT-95502\n- STANDARD -\nArBir 200-5163\nBlack\nPT-95503\n- STANDARD -\nArBir 200-5164\nSax\nPT-57972\n- STANDARD -\nArBir 200-5165\nHome\n>\nProducts\n>\nProtection\n>\nArBir-200\nAPPAREL TEXTILES\nBUILDING TECHNICAL TEXTILES\nHOME TECHNICAL TEXTILES\nPROTECTION TECHNICAL TEXTILES\nMEDICAL TECHNICAL TEXTILES\nSPORT TECHNICAL TEXTILES\nTRANSPORT TECHNICAL TEXTILES\nARITEKS GROUP\nSERVICES\nUV PROTECTION\nFLAME RETARDANT\nINSECT REPELLENT\nANTIBACTERIAL\nWATER REPELLENT\nARDILIGHT\nARNEO ECO\nAROF FILE\nAriteks Headquarters\nPhone:\n+90 212 538 05 98\nAddress:\nOtakçılar Cad. No:80/32 34050\nEyupsultan/Istanbul Turkiye\nE-Mail:\nsupport@ariteksinfo.com\nWeb:\nwww.ariteks.net\nCopyright © 2026 Arıteks A.Ş.",
  "raw_html_local_path": "C:\\Projekty\\galia-navi\\_scraped\\fabrics_complete\\arbir-200\\raw\\product_page.html",
  "url_slug": "arbir-200",
  "display_slug": "arbir-200",
  "spec_quality": {
    "cleaned_by": "crawl_ariteks_fabric_complete_v9",
    "original_had_narrative": true,
    "spec_line_length": 62,
    "cleaned_by_v10": true,
    "v10_changed": true
  }
}