[
  {
    "url": "https://www.ariteks.net/images/product/armedi_antibac_ver2_s.jpg",
    "kind": "image",
    "folder": "images",
    "filename": "armedi-antibac-ver2-s__fb01182994.jpg",
    "raw_local_path": "E:\\ariteks\\new\\medical\\_scraped\\fabrics_complete\\arox-t2-wr-antibac\\images\\armedi-antibac-ver2-s__fb01182994.jpg",
    "status": 200,
    "content_type": "image/jpeg",
    "size_bytes": 48054,
    "sha1": "6e8ea14488b2e0e931b651c4ef488390ae8965b2",
    "error": "",
    "public_local_path": "E:\\ariteks\\new\\medical\\public\\ariteks\\fabrics\\arox-t2-wr-antibac\\images\\armedi-antibac-ver2-s__fb01182994.jpg",
    "public_url": "/ariteks/fabrics/arox-t2-wr-antibac/images/armedi-antibac-ver2-s__fb01182994.jpg"
  },
  {
    "url": "https://www.ariteks.net/pdf/ArMedi_antibac_ru_ds_ver2.pdf",
    "kind": "document",
    "folder": "documents",
    "filename": "armedi-antibac-ru-ds-ver2__4f5fce4a55.pdf",
    "raw_local_path": "E:\\ariteks\\new\\medical\\_scraped\\fabrics_complete\\arox-t2-wr-antibac\\documents\\armedi-antibac-ru-ds-ver2__4f5fce4a55.pdf",
    "status": 200,
    "content_type": "application/pdf",
    "size_bytes": 120148,
    "sha1": "e9e6059ba1244c682d5a8411157d3d45e904b289",
    "error": "",
    "public_local_path": "E:\\ariteks\\new\\medical\\public\\ariteks\\fabrics\\arox-t2-wr-antibac\\documents\\armedi-antibac-ru-ds-ver2__4f5fce4a55.pdf",
    "public_url": "/ariteks/fabrics/arox-t2-wr-antibac/documents/armedi-antibac-ru-ds-ver2__4f5fce4a55.pdf"
  },
  {
    "url": "https://www.ariteks.net/images/functions/en_4920.jpg",
    "kind": "image",
    "folder": "images",
    "filename": "en-4920__7d4ebdfef0.jpg",
    "raw_local_path": "E:\\ariteks\\new\\medical\\_scraped\\fabrics_complete\\arox-t2-wr-antibac\\images\\en-4920__7d4ebdfef0.jpg",
    "status": 200,
    "content_type": "image/jpeg",
    "size_bytes": 5831,
    "sha1": "d2ff279f0bcdc1643e9ccc20fd02ecf4d516ba72",
    "error": "",
    "public_local_path": "E:\\ariteks\\new\\medical\\public\\ariteks\\fabrics\\arox-t2-wr-antibac\\images\\en-4920__7d4ebdfef0.jpg",
    "public_url": "/ariteks/fabrics/arox-t2-wr-antibac/images/en-4920__7d4ebdfef0.jpg"
  },
  {
    "url": "https://www.ariteks.net/images/functions/antibacterial.jpg",
    "kind": "image",
    "folder": "images",
    "filename": "antibacterial__df46a11430.jpg",
    "raw_local_path": "E:\\ariteks\\new\\medical\\_scraped\\fabrics_complete\\arox-t2-wr-antibac\\images\\antibacterial__df46a11430.jpg",
    "status": 200,
    "content_type": "image/jpeg",
    "size_bytes": 8012,
    "sha1": "29a7b6366a22a42fa00b67a355c04fe7f6265944",
    "error": "",
    "public_local_path": "E:\\ariteks\\new\\medical\\public\\ariteks\\fabrics\\arox-t2-wr-antibac\\images\\antibacterial__df46a11430.jpg",
    "public_url": "/ariteks/fabrics/arox-t2-wr-antibac/images/antibacterial__df46a11430.jpg"
  },
  {
    "url": "https://www.ariteks.net/images/functions/iso_18184.jpg",
    "kind": "image",
    "folder": "images",
    "filename": "iso-18184__515a741c33.jpg",
    "raw_local_path": "E:\\ariteks\\new\\medical\\_scraped\\fabrics_complete\\arox-t2-wr-antibac\\images\\iso-18184__515a741c33.jpg",
    "status": 200,
    "content_type": "image/jpeg",
    "size_bytes": 8595,
    "sha1": "659460fe9c079533013335192cee2ac5e62bd666",
    "error": "",
    "public_local_path": "E:\\ariteks\\new\\medical\\public\\ariteks\\fabrics\\arox-t2-wr-antibac\\images\\iso-18184__515a741c33.jpg",
    "public_url": "/ariteks/fabrics/arox-t2-wr-antibac/images/iso-18184__515a741c33.jpg"
  },
  {
    "url": "https://www.ariteks.net/images/structures/woven.jpg",
    "kind": "image",
    "folder": "images",
    "filename": "woven__c0215fa432.jpg",
    "raw_local_path": "E:\\ariteks\\new\\medical\\_scraped\\fabrics_complete\\arox-t2-wr-antibac\\images\\woven__c0215fa432.jpg",
    "status": 200,
    "content_type": "image/jpeg",
    "size_bytes": 21209,
    "sha1": "0c23b895ad29c6a17455b859edcb969daed59fd0",
    "error": "",
    "public_local_path": "E:\\ariteks\\new\\medical\\public\\ariteks\\fabrics\\arox-t2-wr-antibac\\images\\woven__c0215fa432.jpg",
    "public_url": "/ariteks/fabrics/arox-t2-wr-antibac/images/woven__c0215fa432.jpg"
  },
  {
    "url": "https://www.ariteks.net/images/lang_flags/tr_s.png",
    "kind": "image",
    "folder": "images",
    "filename": "tr-s__2229569dd5.png",
    "raw_local_path": "E:\\ariteks\\new\\medical\\_scraped\\fabrics_complete\\arox-t2-wr-antibac\\images\\tr-s__2229569dd5.png",
    "status": 200,
    "content_type": "image/png",
    "size_bytes": 17432,
    "sha1": "bd65b8e80542cd227cd4804519f1b2f5475ab5ac",
    "error": "",
    "public_local_path": "E:\\ariteks\\new\\medical\\public\\ariteks\\fabrics\\arox-t2-wr-antibac\\images\\tr-s__2229569dd5.png",
    "public_url": "/ariteks/fabrics/arox-t2-wr-antibac/images/tr-s__2229569dd5.png"
  },
  {
    "url": "https://www.ariteks.net/images/lang_flags/ru_s.png",
    "kind": "image",
    "folder": "images",
    "filename": "ru-s__28dde2a24b.png",
    "raw_local_path": "E:\\ariteks\\new\\medical\\_scraped\\fabrics_complete\\arox-t2-wr-antibac\\images\\ru-s__28dde2a24b.png",
    "status": 200,
    "content_type": "image/png",
    "size_bytes": 11546,
    "sha1": "32c5e6a1b5d35279db604afc74155714d4620697",
    "error": "",
    "public_local_path": "E:\\ariteks\\new\\medical\\public\\ariteks\\fabrics\\arox-t2-wr-antibac\\images\\ru-s__28dde2a24b.png",
    "public_url": "/ariteks/fabrics/arox-t2-wr-antibac/images/ru-s__28dde2a24b.png"
  },
  {
    "url": "https://www.ariteks.net/images/lang_flags/en_s.png",
    "kind": "image",
    "folder": "images",
    "filename": "en-s__0126e84202.png",
    "raw_local_path": "E:\\ariteks\\new\\medical\\_scraped\\fabrics_complete\\arox-t2-wr-antibac\\images\\en-s__0126e84202.png",
    "status": 200,
    "content_type": "image/png",
    "size_bytes": 19703,
    "sha1": "39e2601f0ea48218abc98576c338648d16b981eb",
    "error": "",
    "public_local_path": "E:\\ariteks\\new\\medical\\public\\ariteks\\fabrics\\arox-t2-wr-antibac\\images\\en-s__0126e84202.png",
    "public_url": "/ariteks/fabrics/arox-t2-wr-antibac/images/en-s__0126e84202.png"
  },
  {
    "url": "https://www.ariteks.net/images/logo/ariteks_logo_2023_en_s.jpg",
    "kind": "image",
    "folder": "images",
    "filename": "ariteks-logo-2023-en-s__6098ac7c7f.jpg",
    "raw_local_path": "E:\\ariteks\\new\\medical\\_scraped\\fabrics_complete\\arox-t2-wr-antibac\\images\\ariteks-logo-2023-en-s__6098ac7c7f.jpg",
    "status": 200,
    "content_type": "image/jpeg",
    "size_bytes": 38222,
    "sha1": "7ed77fbb457d1d6a54526ef032e0ea51a86af3da",
    "error": "",
    "public_local_path": "E:\\ariteks\\new\\medical\\public\\ariteks\\fabrics\\arox-t2-wr-antibac\\images\\ariteks-logo-2023-en-s__6098ac7c7f.jpg",
    "public_url": "/ariteks/fabrics/arox-t2-wr-antibac/images/ariteks-logo-2023-en-s__6098ac7c7f.jpg"
  },
  {
    "url": "https://www.ariteks.net/images/techteksposters/medical_m.jpg",
    "kind": "image",
    "folder": "images",
    "filename": "medical-m__ea2073e222.jpg",
    "raw_local_path": "E:\\ariteks\\new\\medical\\_scraped\\fabrics_complete\\arox-t2-wr-antibac\\images\\medical-m__ea2073e222.jpg",
    "status": 200,
    "content_type": "image/jpeg",
    "size_bytes": 1851288,
    "sha1": "c12cc8e357c9456abbb4a5875757b7df3835ae67",
    "error": "",
    "public_local_path": "E:\\ariteks\\new\\medical\\public\\ariteks\\fabrics\\arox-t2-wr-antibac\\images\\medical-m__ea2073e222.jpg",
    "public_url": "/ariteks/fabrics/arox-t2-wr-antibac/images/medical-m__ea2073e222.jpg"
  },
  {
    "url": "https://www.ariteks.net/images/product/arox_t2_wr_antibac_main_pic_m.jpg",
    "kind": "image",
    "folder": "images",
    "filename": "arox-t2-wr-antibac-main-pic-m__32a419cf64.jpg",
    "raw_local_path": "E:\\ariteks\\new\\medical\\_scraped\\fabrics_complete\\arox-t2-wr-antibac\\images\\arox-t2-wr-antibac-main-pic-m__32a419cf64.jpg",
    "status": 200,
    "content_type": "image/jpeg",
    "size_bytes": 90909,
    "sha1": "4dbd2bbff11329d578003a321f38b57230243791",
    "error": "",
    "public_local_path": "E:\\ariteks\\new\\medical\\public\\ariteks\\fabrics\\arox-t2-wr-antibac\\images\\arox-t2-wr-antibac-main-pic-m__32a419cf64.jpg",
    "public_url": "/ariteks/fabrics/arox-t2-wr-antibac/images/arox-t2-wr-antibac-main-pic-m__32a419cf64.jpg"
  },
  {
    "url": "https://www.ariteks.net/images/certificate/emty_certificate_s.jpg",
    "kind": "image",
    "folder": "images",
    "filename": "emty-certificate-s__f21d0e8c4e.jpg",
    "raw_local_path": "E:\\ariteks\\new\\medical\\_scraped\\fabrics_complete\\arox-t2-wr-antibac\\images\\emty-certificate-s__f21d0e8c4e.jpg",
    "status": 200,
    "content_type": "image/jpeg",
    "size_bytes": 450,
    "sha1": "e1055ecd72dc9e9ff6c0c2a0421537b9bb4d412a",
    "error": "",
    "public_local_path": "E:\\ariteks\\new\\medical\\public\\ariteks\\fabrics\\arox-t2-wr-antibac\\images\\emty-certificate-s__f21d0e8c4e.jpg",
    "public_url": "/ariteks/fabrics/arox-t2-wr-antibac/images/emty-certificate-s__f21d0e8c4e.jpg"
  },
  {
    "url": "https://www.ariteks.net/images/product/medical/silver-pro-mask-en149-ffp2-en18184-antiviral-antibacterial-black-color-m.jpg",
    "kind": "image",
    "folder": "images",
    "filename": "silver-pro-mask-en149-ffp2-en18184-antiviral-antibacterial-black-color-m__65c551776b.jpg",
    "raw_local_path": "E:\\ariteks\\new\\medical\\_scraped\\fabrics_complete\\arox-t2-wr-antibac\\images\\silver-pro-mask-en149-ffp2-en18184-antiviral-antibacterial-black-color-m__65c551776b.jpg",
    "status": 200,
    "content_type": "image/jpeg",
    "size_bytes": 480054,
    "sha1": "be0797109968c858401d28e16ed5f3218f83c5b1",
    "error": "",
    "public_local_path": "E:\\ariteks\\new\\medical\\public\\ariteks\\fabrics\\arox-t2-wr-antibac\\images\\silver-pro-mask-en149-ffp2-en18184-antiviral-antibacterial-black-color-m__65c551776b.jpg",
    "public_url": "/ariteks/fabrics/arox-t2-wr-antibac/images/silver-pro-mask-en149-ffp2-en18184-antiviral-antibacterial-black-color-m__65c551776b.jpg"
  },
  {
    "url": "https://www.ariteks.net/images/product/medical/silver-pro-mask-en14683-en18184-antiviral-antibacterial-blue-color-m.jpg",
    "kind": "image",
    "folder": "images",
    "filename": "silver-pro-mask-en14683-en18184-antiviral-antibacterial-blue-color-m__12b25c334c.jpg",
    "raw_local_path": "E:\\ariteks\\new\\medical\\_scraped\\fabrics_complete\\arox-t2-wr-antibac\\images\\silver-pro-mask-en14683-en18184-antiviral-antibacterial-blue-color-m__12b25c334c.jpg",
    "status": 200,
    "content_type": "image/jpeg",
    "size_bytes": 480054,
    "sha1": "454e23cba5aaa8d31092828524c143b4998f249d",
    "error": "",
    "public_local_path": "E:\\ariteks\\new\\medical\\public\\ariteks\\fabrics\\arox-t2-wr-antibac\\images\\silver-pro-mask-en14683-en18184-antiviral-antibacterial-blue-color-m__12b25c334c.jpg",
    "public_url": "/ariteks/fabrics/arox-t2-wr-antibac/images/silver-pro-mask-en14683-en18184-antiviral-antibacterial-blue-color-m__12b25c334c.jpg"
  },
  {
    "url": "https://www.ariteks.net/images/product/medical/silver-pro-mask-en14683-en18184-antiviral-antibacterial-red-color-m.jpg",
    "kind": "image",
    "folder": "images",
    "filename": "silver-pro-mask-en14683-en18184-antiviral-antibacterial-red-color-m__871b69e115.jpg",
    "raw_local_path": "E:\\ariteks\\new\\medical\\_scraped\\fabrics_complete\\arox-t2-wr-antibac\\images\\silver-pro-mask-en14683-en18184-antiviral-antibacterial-red-color-m__871b69e115.jpg",
    "status": 200,
    "content_type": "image/jpeg",
    "size_bytes": 480054,
    "sha1": "e47e0341b600589c350d66b25e59acb3126f4391",
    "error": "",
    "public_local_path": "E:\\ariteks\\new\\medical\\public\\ariteks\\fabrics\\arox-t2-wr-antibac\\images\\silver-pro-mask-en14683-en18184-antiviral-antibacterial-red-color-m__871b69e115.jpg",
    "public_url": "/ariteks/fabrics/arox-t2-wr-antibac/images/silver-pro-mask-en14683-en18184-antiviral-antibacterial-red-color-m__871b69e115.jpg"
  },
  {
    "url": "https://www.ariteks.net/images/functions/oekoteks_standard_100_s.jpg",
    "kind": "image",
    "folder": "images",
    "filename": "oekoteks-standard-100-s__ea5e91d474.jpg",
    "raw_local_path": "E:\\ariteks\\new\\medical\\_scraped\\fabrics_complete\\arox-t2-wr-antibac\\images\\oekoteks-standard-100-s__ea5e91d474.jpg",
    "status": 200,
    "content_type": "image/jpeg",
    "size_bytes": 54001,
    "sha1": "66018f06a237c3ddcbf31a5764c82e862dfa9854",
    "error": "",
    "public_local_path": "E:\\ariteks\\new\\medical\\public\\ariteks\\fabrics\\arox-t2-wr-antibac\\images\\oekoteks-standard-100-s__ea5e91d474.jpg",
    "public_url": "/ariteks/fabrics/arox-t2-wr-antibac/images/oekoteks-standard-100-s__ea5e91d474.jpg"
  },
  {
    "url": "https://www.ariteks.net/images/care_instructions/60_mach_wash_ma_agi.jpg",
    "kind": "image",
    "folder": "images",
    "filename": "60-mach-wash-ma-agi__cdc86ecf03.jpg",
    "raw_local_path": "E:\\ariteks\\new\\medical\\_scraped\\fabrics_complete\\arox-t2-wr-antibac\\images\\60-mach-wash-ma-agi__cdc86ecf03.jpg",
    "status": 200,
    "content_type": "image/jpeg",
    "size_bytes": 97254,
    "sha1": "5172828b46e8d14500d23799c64ca5370bcf514b",
    "error": "",
    "public_local_path": "E:\\ariteks\\new\\medical\\public\\ariteks\\fabrics\\arox-t2-wr-antibac\\images\\60-mach-wash-ma-agi__cdc86ecf03.jpg",
    "public_url": "/ariteks/fabrics/arox-t2-wr-antibac/images/60-mach-wash-ma-agi__cdc86ecf03.jpg"
  },
  {
    "url": "https://www.ariteks.net/images/care_instructions/no_chlorine_bleach.jpg",
    "kind": "image",
    "folder": "images",
    "filename": "no-chlorine-bleach__33a0308671.jpg",
    "raw_local_path": "E:\\ariteks\\new\\medical\\_scraped\\fabrics_complete\\arox-t2-wr-antibac\\images\\no-chlorine-bleach__33a0308671.jpg",
    "status": 200,
    "content_type": "image/jpeg",
    "size_bytes": 97254,
    "sha1": "04121b8c5d4d25547de9c83657618e8fa04d2e52",
    "error": "",
    "public_local_path": "E:\\ariteks\\new\\medical\\public\\ariteks\\fabrics\\arox-t2-wr-antibac\\images\\no-chlorine-bleach__33a0308671.jpg",
    "public_url": "/ariteks/fabrics/arox-t2-wr-antibac/images/no-chlorine-bleach__33a0308671.jpg"
  },
  {
    "url": "https://www.ariteks.net/images/care_instructions/tumble_dried_low_ht.jpg",
    "kind": "image",
    "folder": "images",
    "filename": "tumble-dried-low-ht__cd432a52a7.jpg",
    "raw_local_path": "E:\\ariteks\\new\\medical\\_scraped\\fabrics_complete\\arox-t2-wr-antibac\\images\\tumble-dried-low-ht__cd432a52a7.jpg",
    "status": 200,
    "content_type": "image/jpeg",
    "size_bytes": 97254,
    "sha1": "b5fb112a29efca36c0a736eb588a8a367fb30bac",
    "error": "",
    "public_local_path": "E:\\ariteks\\new\\medical\\public\\ariteks\\fabrics\\arox-t2-wr-antibac\\images\\tumble-dried-low-ht__cd432a52a7.jpg",
    "public_url": "/ariteks/fabrics/arox-t2-wr-antibac/images/tumble-dried-low-ht__cd432a52a7.jpg"
  },
  {
    "url": "https://www.ariteks.net/images/care_instructions/ma_150_iron.jpg",
    "kind": "image",
    "folder": "images",
    "filename": "ma-150-iron__78883199be.jpg",
    "raw_local_path": "E:\\ariteks\\new\\medical\\_scraped\\fabrics_complete\\arox-t2-wr-antibac\\images\\ma-150-iron__78883199be.jpg",
    "status": 200,
    "content_type": "image/jpeg",
    "size_bytes": 97794,
    "sha1": "f5a4fac2b95005ea49edbeb1b6de2be8abcea782",
    "error": "",
    "public_local_path": "E:\\ariteks\\new\\medical\\public\\ariteks\\fabrics\\arox-t2-wr-antibac\\images\\ma-150-iron__78883199be.jpg",
    "public_url": "/ariteks/fabrics/arox-t2-wr-antibac/images/ma-150-iron__78883199be.jpg"
  },
  {
    "url": "https://www.ariteks.net/images/care_instructions/dry_cleaning.jpg",
    "kind": "image",
    "folder": "images",
    "filename": "dry-cleaning__6e8a85520f.jpg",
    "raw_local_path": "E:\\ariteks\\new\\medical\\_scraped\\fabrics_complete\\arox-t2-wr-antibac\\images\\dry-cleaning__6e8a85520f.jpg",
    "status": 200,
    "content_type": "image/jpeg",
    "size_bytes": 97254,
    "sha1": "d8d03b8658bc4f973c36cb18f135e6b56f318f6c",
    "error": "",
    "public_local_path": "E:\\ariteks\\new\\medical\\public\\ariteks\\fabrics\\arox-t2-wr-antibac\\images\\dry-cleaning__6e8a85520f.jpg",
    "public_url": "/ariteks/fabrics/arox-t2-wr-antibac/images/dry-cleaning__6e8a85520f.jpg"
  },
  {
    "url": "https://www.ariteks.net/pdf/arox-t2-wr-antibac-ds.pdf",
    "kind": "document",
    "folder": "documents",
    "filename": "arox-t2-wr-antibac-ds__6f9ec2cb66.pdf",
    "raw_local_path": "E:\\ariteks\\new\\medical\\_scraped\\fabrics_complete\\arox-t2-wr-antibac\\documents\\arox-t2-wr-antibac-ds__6f9ec2cb66.pdf",
    "status": 200,
    "content_type": "application/pdf",
    "size_bytes": 326302,
    "sha1": "1b671c11a9faa594a11fd72cfaff121f3361b958",
    "error": "",
    "public_local_path": "E:\\ariteks\\new\\medical\\public\\ariteks\\fabrics\\arox-t2-wr-antibac\\documents\\arox-t2-wr-antibac-ds__6f9ec2cb66.pdf",
    "public_url": "/ariteks/fabrics/arox-t2-wr-antibac/documents/arox-t2-wr-antibac-ds__6f9ec2cb66.pdf"
  },
  {
    "url": "https://www.ariteks.net/images/certificate/arox-t2-wr-antibac-en-3071-tr.pdf",
    "kind": "document",
    "folder": "documents",
    "filename": "arox-t2-wr-antibac-en-3071-tr__4a16985d1d.pdf",
    "raw_local_path": "E:\\ariteks\\new\\medical\\_scraped\\fabrics_complete\\arox-t2-wr-antibac\\documents\\arox-t2-wr-antibac-en-3071-tr__4a16985d1d.pdf",
    "status": 200,
    "content_type": "application/pdf",
    "size_bytes": 276600,
    "sha1": "0b7c6f06b13263a8862996fbccd81012285925b4",
    "error": "",
    "public_local_path": "E:\\ariteks\\new\\medical\\public\\ariteks\\fabrics\\arox-t2-wr-antibac\\documents\\arox-t2-wr-antibac-en-3071-tr__4a16985d1d.pdf",
    "public_url": "/ariteks/fabrics/arox-t2-wr-antibac/documents/arox-t2-wr-antibac-en-3071-tr__4a16985d1d.pdf"
  },
  {
    "url": "https://www.ariteks.net/images/certificate/arox-t2-wr-antibac-en-3071-en.pdf",
    "kind": "document",
    "folder": "documents",
    "filename": "arox-t2-wr-antibac-en-3071-en__3279750f01.pdf",
    "raw_local_path": "E:\\ariteks\\new\\medical\\_scraped\\fabrics_complete\\arox-t2-wr-antibac\\documents\\arox-t2-wr-antibac-en-3071-en__3279750f01.pdf",
    "status": 200,
    "content_type": "application/pdf",
    "size_bytes": 232879,
    "sha1": "996de826016e8d8406a96597648117ba92bf513f",
    "error": "",
    "public_local_path": "E:\\ariteks\\new\\medical\\public\\ariteks\\fabrics\\arox-t2-wr-antibac\\documents\\arox-t2-wr-antibac-en-3071-en__3279750f01.pdf",
    "public_url": "/ariteks/fabrics/arox-t2-wr-antibac/documents/arox-t2-wr-antibac-en-3071-en__3279750f01.pdf"
  },
  {
    "url": "https://www.ariteks.net/images/certificate/arox-t2-wr-antibac-iso-6330-en.pdf",
    "kind": "document",
    "folder": "documents",
    "filename": "arox-t2-wr-antibac-iso-6330-en__e2e129cb89.pdf",
    "raw_local_path": "E:\\ariteks\\new\\medical\\_scraped\\fabrics_complete\\arox-t2-wr-antibac\\documents\\arox-t2-wr-antibac-iso-6330-en__e2e129cb89.pdf",
    "status": 200,
    "content_type": "application/pdf",
    "size_bytes": 258391,
    "sha1": "87145242279b9eae21f84ff3a1dd0a11d207b02f",
    "error": "",
    "public_local_path": "E:\\ariteks\\new\\medical\\public\\ariteks\\fabrics\\arox-t2-wr-antibac\\documents\\arox-t2-wr-antibac-iso-6330-en__e2e129cb89.pdf",
    "public_url": "/ariteks/fabrics/arox-t2-wr-antibac/documents/arox-t2-wr-antibac-iso-6330-en__e2e129cb89.pdf"
  },
  {
    "url": "https://www.ariteks.net/images/certificate/arox-t2-wr-antibac-en-14362-1-tr.pdf",
    "kind": "document",
    "folder": "documents",
    "filename": "arox-t2-wr-antibac-en-14362-1-tr__568c68429c.pdf",
    "raw_local_path": "E:\\ariteks\\new\\medical\\_scraped\\fabrics_complete\\arox-t2-wr-antibac\\documents\\arox-t2-wr-antibac-en-14362-1-tr__568c68429c.pdf",
    "status": 200,
    "content_type": "application/pdf",
    "size_bytes": 365474,
    "sha1": "36a97c9892da654f09182097311966a8ea80a738",
    "error": "",
    "public_local_path": "E:\\ariteks\\new\\medical\\public\\ariteks\\fabrics\\arox-t2-wr-antibac\\documents\\arox-t2-wr-antibac-en-14362-1-tr__568c68429c.pdf",
    "public_url": "/ariteks/fabrics/arox-t2-wr-antibac/documents/arox-t2-wr-antibac-en-14362-1-tr__568c68429c.pdf"
  },
  {
    "url": "https://www.ariteks.net/images/certificate/arox-t2-wr-antibac-en-14362-1-en.pdf",
    "kind": "document",
    "folder": "documents",
    "filename": "arox-t2-wr-antibac-en-14362-1-en__62a7b994bb.pdf",
    "raw_local_path": "E:\\ariteks\\new\\medical\\_scraped\\fabrics_complete\\arox-t2-wr-antibac\\documents\\arox-t2-wr-antibac-en-14362-1-en__62a7b994bb.pdf",
    "status": 200,
    "content_type": "application/pdf",
    "size_bytes": 304955,
    "sha1": "457cab56e735c9acc6ddce7077383a001ccc7621",
    "error": "",
    "public_local_path": "E:\\ariteks\\new\\medical\\public\\ariteks\\fabrics\\arox-t2-wr-antibac\\documents\\arox-t2-wr-antibac-en-14362-1-en__62a7b994bb.pdf",
    "public_url": "/ariteks/fabrics/arox-t2-wr-antibac/documents/arox-t2-wr-antibac-en-14362-1-en__62a7b994bb.pdf"
  },
  {
    "url": "https://www.ariteks.net/images/certificate/arox-t2-wr-antibac-iso105-d01-en.pdf",
    "kind": "document",
    "folder": "documents",
    "filename": "arox-t2-wr-antibac-iso105-d01-en__3e0299ad69.pdf",
    "raw_local_path": "E:\\ariteks\\new\\medical\\_scraped\\fabrics_complete\\arox-t2-wr-antibac\\documents\\arox-t2-wr-antibac-iso105-d01-en__3e0299ad69.pdf",
    "status": 200,
    "content_type": "application/pdf",
    "size_bytes": 261256,
    "sha1": "defd92b3854ac78eaf7cf304feb868b3294bbeab",
    "error": "",
    "public_local_path": "E:\\ariteks\\new\\medical\\public\\ariteks\\fabrics\\arox-t2-wr-antibac\\documents\\arox-t2-wr-antibac-iso105-d01-en__3e0299ad69.pdf",
    "public_url": "/ariteks/fabrics/arox-t2-wr-antibac/documents/arox-t2-wr-antibac-iso105-d01-en__3e0299ad69.pdf"
  },
  {
    "url": "https://www.ariteks.net/images/certificate/arox-t2-wr-antibac-iso105-n01-en.pdf",
    "kind": "document",
    "folder": "documents",
    "filename": "arox-t2-wr-antibac-iso105-n01-en__da7bda9a59.pdf",
    "raw_local_path": "E:\\ariteks\\new\\medical\\_scraped\\fabrics_complete\\arox-t2-wr-antibac\\documents\\arox-t2-wr-antibac-iso105-n01-en__da7bda9a59.pdf",
    "status": null,
    "content_type": "",
    "size_bytes": 0,
    "sha1": "",
    "error": "500 Server Error: Internal Server Error for url: https://www.ariteks.net/images/certificate/arox-t2-wr-antibac-iso105-n01-en.pdf",
    "public_local_path": "",
    "public_url": ""
  },
  {
    "url": "https://www.ariteks.net/images/certificate/arox-t2-wr-antibac-iso-105-x11-tr.pdf",
    "kind": "document",
    "folder": "documents",
    "filename": "arox-t2-wr-antibac-iso-105-x11-tr__56747a2a82.pdf",
    "raw_local_path": "E:\\ariteks\\new\\medical\\_scraped\\fabrics_complete\\arox-t2-wr-antibac\\documents\\arox-t2-wr-antibac-iso-105-x11-tr__56747a2a82.pdf",
    "status": 200,
    "content_type": "application/pdf",
    "size_bytes": 258571,
    "sha1": "a254c28e9c6de666ab06fbf673c73ecb21da2c9b",
    "error": "",
    "public_local_path": "E:\\ariteks\\new\\medical\\public\\ariteks\\fabrics\\arox-t2-wr-antibac\\documents\\arox-t2-wr-antibac-iso-105-x11-tr__56747a2a82.pdf",
    "public_url": "/ariteks/fabrics/arox-t2-wr-antibac/documents/arox-t2-wr-antibac-iso-105-x11-tr__56747a2a82.pdf"
  },
  {
    "url": "https://www.ariteks.net/images/certificate/arox-t2-wr-antibac-iso-105-x11-en.pdf",
    "kind": "document",
    "folder": "documents",
    "filename": "arox-t2-wr-antibac-iso-105-x11-en__d91934be98.pdf",
    "raw_local_path": "E:\\ariteks\\new\\medical\\_scraped\\fabrics_complete\\arox-t2-wr-antibac\\documents\\arox-t2-wr-antibac-iso-105-x11-en__d91934be98.pdf",
    "status": 200,
    "content_type": "application/pdf",
    "size_bytes": 258571,
    "sha1": "a254c28e9c6de666ab06fbf673c73ecb21da2c9b",
    "error": "",
    "public_local_path": "E:\\ariteks\\new\\medical\\public\\ariteks\\fabrics\\arox-t2-wr-antibac\\documents\\arox-t2-wr-antibac-iso-105-x11-tr__56747a2a82.pdf",
    "public_url": "/ariteks/fabrics/arox-t2-wr-antibac/documents/arox-t2-wr-antibac-iso-105-x11-tr__56747a2a82.pdf"
  },
  {
    "url": "https://www.ariteks.net/images/certificate/arox-t2-wr-antibac-iso-105-x12-en.pdf",
    "kind": "document",
    "folder": "documents",
    "filename": "arox-t2-wr-antibac-iso-105-x12-en__dc63c93f4e.pdf",
    "raw_local_path": "E:\\ariteks\\new\\medical\\_scraped\\fabrics_complete\\arox-t2-wr-antibac\\documents\\arox-t2-wr-antibac-iso-105-x12-en__dc63c93f4e.pdf",
    "status": 200,
    "content_type": "application/pdf",
    "size_bytes": 256045,
    "sha1": "c47f67bf076ce21518adae2b971672b44141cb4a",
    "error": "",
    "public_local_path": "E:\\ariteks\\new\\medical\\public\\ariteks\\fabrics\\arox-t2-wr-antibac\\documents\\arox-t2-wr-antibac-iso-105-x12-en__dc63c93f4e.pdf",
    "public_url": "/ariteks/fabrics/arox-t2-wr-antibac/documents/arox-t2-wr-antibac-iso-105-x12-en__dc63c93f4e.pdf"
  },
  {
    "url": "https://www.ariteks.net/images/certificate/arox-t2-wr-antibac-iso-13934-1-en.pdf",
    "kind": "document",
    "folder": "documents",
    "filename": "arox-t2-wr-antibac-iso-13934-1-en__82cd524757.pdf",
    "raw_local_path": "E:\\ariteks\\new\\medical\\_scraped\\fabrics_complete\\arox-t2-wr-antibac\\documents\\arox-t2-wr-antibac-iso-13934-1-en__82cd524757.pdf",
    "status": 200,
    "content_type": "application/pdf",
    "size_bytes": 257444,
    "sha1": "eaebd8fa5a267dc2b2fb338abfbdd3ed16711a6f",
    "error": "",
    "public_local_path": "E:\\ariteks\\new\\medical\\public\\ariteks\\fabrics\\arox-t2-wr-antibac\\documents\\arox-t2-wr-antibac-iso-13934-1-en__82cd524757.pdf",
    "public_url": "/ariteks/fabrics/arox-t2-wr-antibac/documents/arox-t2-wr-antibac-iso-13934-1-en__82cd524757.pdf"
  },
  {
    "url": "https://www.ariteks.net/images/certificate/arox-t2-wr-antibac-iso-13934-1-N-en.pdf",
    "kind": "document",
    "folder": "documents",
    "filename": "arox-t2-wr-antibac-iso-13934-1-n-en__bda0904240.pdf",
    "raw_local_path": "E:\\ariteks\\new\\medical\\_scraped\\fabrics_complete\\arox-t2-wr-antibac\\documents\\arox-t2-wr-antibac-iso-13934-1-n-en__bda0904240.pdf",
    "status": 200,
    "content_type": "application/pdf",
    "size_bytes": 257660,
    "sha1": "ea7f4b1dc7fb376f5c619fd9e0d65edf9567fef7",
    "error": "",
    "public_local_path": "E:\\ariteks\\new\\medical\\public\\ariteks\\fabrics\\arox-t2-wr-antibac\\documents\\arox-t2-wr-antibac-iso-13934-1-n-en__bda0904240.pdf",
    "public_url": "/ariteks/fabrics/arox-t2-wr-antibac/documents/arox-t2-wr-antibac-iso-13934-1-n-en__bda0904240.pdf"
  },
  {
    "url": "https://www.ariteks.net/images/certificate/arox-t2-wr-antibac-en-24920-en.pdf",
    "kind": "document",
    "folder": "documents",
    "filename": "arox-t2-wr-antibac-en-24920-en__b5777e1d06.pdf",
    "raw_local_path": "E:\\ariteks\\new\\medical\\_scraped\\fabrics_complete\\arox-t2-wr-antibac\\documents\\arox-t2-wr-antibac-en-24920-en__b5777e1d06.pdf",
    "status": 200,
    "content_type": "application/pdf",
    "size_bytes": 260678,
    "sha1": "13bf8eed7fe59fcc4762077e0077088d5fbc0919",
    "error": "",
    "public_local_path": "E:\\ariteks\\new\\medical\\public\\ariteks\\fabrics\\arox-t2-wr-antibac\\documents\\arox-t2-wr-antibac-en-24920-en__b5777e1d06.pdf",
    "public_url": "/ariteks/fabrics/arox-t2-wr-antibac/documents/arox-t2-wr-antibac-en-24920-en__b5777e1d06.pdf"
  },
  {
    "url": "https://www.ariteks.net/images/certificate/arox-t2-wr-antibac-iso-105-e04-en.pdf",
    "kind": "document",
    "folder": "documents",
    "filename": "arox-t2-wr-antibac-iso-105-e04-en__839018401f.pdf",
    "raw_local_path": "E:\\ariteks\\new\\medical\\_scraped\\fabrics_complete\\arox-t2-wr-antibac\\documents\\arox-t2-wr-antibac-iso-105-e04-en__839018401f.pdf",
    "status": 200,
    "content_type": "application/pdf",
    "size_bytes": 263709,
    "sha1": "39f159c1127301729727cbdd2c08f6e580f4300e",
    "error": "",
    "public_local_path": "E:\\ariteks\\new\\medical\\public\\ariteks\\fabrics\\arox-t2-wr-antibac\\documents\\arox-t2-wr-antibac-iso-105-e04-en__839018401f.pdf",
    "public_url": "/ariteks/fabrics/arox-t2-wr-antibac/documents/arox-t2-wr-antibac-iso-105-e04-en__839018401f.pdf"
  },
  {
    "url": "https://www.ariteks.net/images/certificate/arox-t2-wr-antibac-en-13937-2-en.pdf",
    "kind": "document",
    "folder": "documents",
    "filename": "arox-t2-wr-antibac-en-13937-2-en__02317c61ad.pdf",
    "raw_local_path": "E:\\ariteks\\new\\medical\\_scraped\\fabrics_complete\\arox-t2-wr-antibac\\documents\\arox-t2-wr-antibac-en-13937-2-en__02317c61ad.pdf",
    "status": 200,
    "content_type": "application/pdf",
    "size_bytes": 253391,
    "sha1": "2d6fcc1ca8652b0574426f0d3a67ec8327684294",
    "error": "",
    "public_local_path": "E:\\ariteks\\new\\medical\\public\\ariteks\\fabrics\\arox-t2-wr-antibac\\documents\\arox-t2-wr-antibac-en-13937-2-en__02317c61ad.pdf",
    "public_url": "/ariteks/fabrics/arox-t2-wr-antibac/documents/arox-t2-wr-antibac-en-13937-2-en__02317c61ad.pdf"
  },
  {
    "url": "https://www.ariteks.net/images/certificate/arox_t2_wr_antibac_astme_2149_test_report.pdf",
    "kind": "document",
    "folder": "documents",
    "filename": "arox-t2-wr-antibac-astme-2149-test-report__22176b5972.pdf",
    "raw_local_path": "E:\\ariteks\\new\\medical\\_scraped\\fabrics_complete\\arox-t2-wr-antibac\\documents\\arox-t2-wr-antibac-astme-2149-test-report__22176b5972.pdf",
    "status": 200,
    "content_type": "application/pdf",
    "size_bytes": 460047,
    "sha1": "de28ed0e6a95bec61ceb6afdabed4f26cb6f3c60",
    "error": "",
    "public_local_path": "E:\\ariteks\\new\\medical\\public\\ariteks\\fabrics\\arox-t2-wr-antibac\\documents\\arox-t2-wr-antibac-astme-2149-test-report__22176b5972.pdf",
    "public_url": "/ariteks/fabrics/arox-t2-wr-antibac/documents/arox-t2-wr-antibac-astme-2149-test-report__22176b5972.pdf"
  },
  {
    "url": "https://www.ariteks.net/images/certificate/arox_t2_wr_antibac_astme_2149_test_report_2.pdf",
    "kind": "document",
    "folder": "documents",
    "filename": "arox-t2-wr-antibac-astme-2149-test-report-2__5b424396cc.pdf",
    "raw_local_path": "E:\\ariteks\\new\\medical\\_scraped\\fabrics_complete\\arox-t2-wr-antibac\\documents\\arox-t2-wr-antibac-astme-2149-test-report-2__5b424396cc.pdf",
    "status": 200,
    "content_type": "application/pdf",
    "size_bytes": 1333660,
    "sha1": "1762c066f3dca80c1b93a9184b6c983ac95a9d78",
    "error": "",
    "public_local_path": "E:\\ariteks\\new\\medical\\public\\ariteks\\fabrics\\arox-t2-wr-antibac\\documents\\arox-t2-wr-antibac-astme-2149-test-report-2__5b424396cc.pdf",
    "public_url": "/ariteks/fabrics/arox-t2-wr-antibac/documents/arox-t2-wr-antibac-astme-2149-test-report-2__5b424396cc.pdf"
  },
  {
    "url": "https://www.ariteks.net/images/certificate/arox_t2_wr_antibac_astme_2149_test_report_50_wash_en.pdf",
    "kind": "document",
    "folder": "documents",
    "filename": "arox-t2-wr-antibac-astme-2149-test-report-50-wash-en__f4d60e1c00.pdf",
    "raw_local_path": "E:\\ariteks\\new\\medical\\_scraped\\fabrics_complete\\arox-t2-wr-antibac\\documents\\arox-t2-wr-antibac-astme-2149-test-report-50-wash-en__f4d60e1c00.pdf",
    "status": 200,
    "content_type": "application/pdf",
    "size_bytes": 425930,
    "sha1": "91071b4c44a107d3e177b22451c63cc90f8edc17",
    "error": "",
    "public_local_path": "E:\\ariteks\\new\\medical\\public\\ariteks\\fabrics\\arox-t2-wr-antibac\\documents\\arox-t2-wr-antibac-astme-2149-test-report-50-wash-en__f4d60e1c00.pdf",
    "public_url": "/ariteks/fabrics/arox-t2-wr-antibac/documents/arox-t2-wr-antibac-astme-2149-test-report-50-wash-en__f4d60e1c00.pdf"
  },
  {
    "url": "https://www.ariteks.net/images/certificate/arox_t2_wr_antibac_astme_2149_test_report_100_wash_en.pdf",
    "kind": "document",
    "folder": "documents",
    "filename": "arox-t2-wr-antibac-astme-2149-test-report-100-wash-en__d9c767bde5.pdf",
    "raw_local_path": "E:\\ariteks\\new\\medical\\_scraped\\fabrics_complete\\arox-t2-wr-antibac\\documents\\arox-t2-wr-antibac-astme-2149-test-report-100-wash-en__d9c767bde5.pdf",
    "status": 200,
    "content_type": "application/pdf",
    "size_bytes": 422820,
    "sha1": "f9f94769fa02f90e6d4aa5e86e1a4d095e16b580",
    "error": "",
    "public_local_path": "E:\\ariteks\\new\\medical\\public\\ariteks\\fabrics\\arox-t2-wr-antibac\\documents\\arox-t2-wr-antibac-astme-2149-test-report-100-wash-en__d9c767bde5.pdf",
    "public_url": "/ariteks/fabrics/arox-t2-wr-antibac/documents/arox-t2-wr-antibac-astme-2149-test-report-100-wash-en__d9c767bde5.pdf"
  },
  {
    "url": "https://www.ariteks.net/images/certificate/arox_t2_wr_antibac_en_14683.pdf",
    "kind": "document",
    "folder": "documents",
    "filename": "arox-t2-wr-antibac-en-14683__5a57bfcbe5.pdf",
    "raw_local_path": "E:\\ariteks\\new\\medical\\_scraped\\fabrics_complete\\arox-t2-wr-antibac\\documents\\arox-t2-wr-antibac-en-14683__5a57bfcbe5.pdf",
    "status": 200,
    "content_type": "application/pdf",
    "size_bytes": 1533454,
    "sha1": "a4554123d68ece21519bb6d3ab8313c5a07300e3",
    "error": "",
    "public_local_path": "E:\\ariteks\\new\\medical\\public\\ariteks\\fabrics\\arox-t2-wr-antibac\\documents\\arox-t2-wr-antibac-en-14683__5a57bfcbe5.pdf",
    "public_url": "/ariteks/fabrics/arox-t2-wr-antibac/documents/arox-t2-wr-antibac-en-14683__5a57bfcbe5.pdf"
  },
  {
    "url": "https://www.ariteks.net/images/product/medical/silver-pro-mask-en149-ffp2-en18184-antiviral-antibacterial-black-color.jpg",
    "kind": "image",
    "folder": "images",
    "filename": "silver-pro-mask-en149-ffp2-en18184-antiviral-antibacterial-black-color__ac99e57fe0.jpg",
    "raw_local_path": "E:\\ariteks\\new\\medical\\_scraped\\fabrics_complete\\arox-t2-wr-antibac\\images\\silver-pro-mask-en149-ffp2-en18184-antiviral-antibacterial-black-color__ac99e57fe0.jpg",
    "status": 200,
    "content_type": "image/jpeg",
    "size_bytes": 899322,
    "sha1": "e72047fc318a6b7935e22cdb9f76b8da588e0300",
    "error": "",
    "public_local_path": "E:\\ariteks\\new\\medical\\public\\ariteks\\fabrics\\arox-t2-wr-antibac\\images\\silver-pro-mask-en149-ffp2-en18184-antiviral-antibacterial-black-color__ac99e57fe0.jpg",
    "public_url": "/ariteks/fabrics/arox-t2-wr-antibac/images/silver-pro-mask-en149-ffp2-en18184-antiviral-antibacterial-black-color__ac99e57fe0.jpg"
  },
  {
    "url": "https://www.ariteks.net/images/product/medical/silver-pro-mask-en14683-en18184-antiviral-antibacterial-blue-color.jpg",
    "kind": "image",
    "folder": "images",
    "filename": "silver-pro-mask-en14683-en18184-antiviral-antibacterial-blue-color__ba331818c4.jpg",
    "raw_local_path": "E:\\ariteks\\new\\medical\\_scraped\\fabrics_complete\\arox-t2-wr-antibac\\images\\silver-pro-mask-en14683-en18184-antiviral-antibacterial-blue-color__ba331818c4.jpg",
    "status": 200,
    "content_type": "image/jpeg",
    "size_bytes": 895494,
    "sha1": "21aa218239735d9710daa9aef670d394baba4550",
    "error": "",
    "public_local_path": "E:\\ariteks\\new\\medical\\public\\ariteks\\fabrics\\arox-t2-wr-antibac\\images\\silver-pro-mask-en14683-en18184-antiviral-antibacterial-blue-color__ba331818c4.jpg",
    "public_url": "/ariteks/fabrics/arox-t2-wr-antibac/images/silver-pro-mask-en14683-en18184-antiviral-antibacterial-blue-color__ba331818c4.jpg"
  },
  {
    "url": "https://www.ariteks.net/images/product/medical/silver-pro-mask-en14683-en18184-antiviral-antibacterial-red-color.jpg",
    "kind": "image",
    "folder": "images",
    "filename": "silver-pro-mask-en14683-en18184-antiviral-antibacterial-red-color__5820ea858a.jpg",
    "raw_local_path": "E:\\ariteks\\new\\medical\\_scraped\\fabrics_complete\\arox-t2-wr-antibac\\images\\silver-pro-mask-en14683-en18184-antiviral-antibacterial-red-color__5820ea858a.jpg",
    "status": 200,
    "content_type": "image/jpeg",
    "size_bytes": 900966,
    "sha1": "6661219d46d1c536a2b29b42c36ee3c869aa984d",
    "error": "",
    "public_local_path": "E:\\ariteks\\new\\medical\\public\\ariteks\\fabrics\\arox-t2-wr-antibac\\images\\silver-pro-mask-en14683-en18184-antiviral-antibacterial-red-color__5820ea858a.jpg",
    "public_url": "/ariteks/fabrics/arox-t2-wr-antibac/images/silver-pro-mask-en14683-en18184-antiviral-antibacterial-red-color__5820ea858a.jpg"
  }
]